Workbook

Sheet Cover
A1: 万华化学简版化工模型
A2: New period standard: annual 2018A–2025A; quarterly actuals 2024Q1A–2026Q2A; annual forecast 2026E–2028E; quarterly forecast 2026Q3E–2027Q4E
A4: Model identity
A5: Company | B5: 万华化学集团股份有限公司
A6: Ticker | B6: 600309.SH
A7: Currency / unit | B7: RMB mm
A8: Annual history | B8: 2018A–2025A
A9: Quarterly history | B9: 2024Q1A–2026Q2A
A10: Annual forecast | B10: 2026E–2028E
A11: Quarterly forecast | B11: 2026Q3E–2027Q4E
A12: Model date | B12: 2026-08-24
A13: Version | B13: 2026H1 actual update v2.1
A15: Critical boundary notes
A16: Annual actuals use annual reports. Standalone Q2/Q3/Q4 consolidated actuals are arithmetic differences of cumulative primary filings; they are not estimates.
A17: Product-series sales volumes include internal use; apparent ASP is a blended proxy. Product-series revenue includes trade and internal-use revenue.
A18: Quarterly product-series costs are not disclosed and remain blank. No quarterly cost allocation is forced.
A19: Historical hardcodes are blue; formulas black; cross-sheet formulas green; forecast assumptions are yellow.
A20: All forecast passthroughs use IF(source="","",source) or equivalent blank gates.
A22: Color convention
A23: Hardcode / actual | B23: Aa123
A24: Formula | B24: Aa123
A25: Cross-sheet formula | B25: Aa123
A26: External link | B26: Aa123
A27: Forecast assumption | B27: Aa123

Sheet Assumptions
A1: Assumptions
A2: Only forecast columns are input-enabled; all are intentionally blank at hand-off.
A4: RMB mm unless stated | B4: 2018A | C4: 2019A | D4: 2020A | E4: 2021A | F4: 2022A | G4: 2023A | H4: 2024A | I4: 2025A | J4: 2024Q1A | K4: 2024Q2A | L4: 2024Q3A | M4: 2024Q4A | N4: 2025Q1A | O4: 2025Q2A | P4: 2025Q3A | Q4: 2025Q4A | R4: 2026Q1A | S4: 2026E | T4: 2027E | U4: 2028E | V4: 2026Q2A | W4: 2026Q3E | X4: 2026Q4E | Y4: 2027Q1E | Z4: 2027Q2E | AA4: 2027Q3E | AB4: 2027Q4E
A5: 聚氨酯系列
A6: Volume growth
A7: Apparent ASP growth
A8: Raw-material share
A9: Non-raw cost inflation
A11: 石化系列
A12: Volume growth
A13: Apparent ASP growth
A14: Raw-material share
A15: Non-raw cost inflation
A17: 精细化学品及新材料系列
A18: Volume growth
... A31: Capex / revenue

Sheet Price Inputs
A1: Price Inputs
A2: Company-disclosed market averages; blanks preserve missing period disclosures.
A4: RMB mm unless stated | B4: 2018A | C4: 2019A | D4: 2020A | E4: 2021A | F4: 2022A | G4: 2023A | H4: 2024A | I4: 2025A | J4: 2024Q1A | K4: 2024Q2A | L4: 2024Q3A | M4: 2024Q4A | N4: 2025Q1A | O4: 2025Q2A | P4: 2025Q3A | Q4: 2025Q4A | R4: 2026Q1A | S4: 2026E | T4: 2027E | U4: 2028E | V4: 2026Q2A | W4: 2026Q3E | X4: 2026Q4E | Y4: 2027Q1E | Z4: 2027Q2E | AA4: 2027Q3E | AB4: 2027Q4E
A5: Polymeric MDI market average (RMB/t; approx.) | G5: 16000 | H5: 17000 | I5: 16200 | J5: 17000 | L5: 17800 | N5: 17000 | P5: 15200 | R5: 15500 | S5: =IF(Assumptions!S24="","",Assumptions!S24) | T5: =IF(Assumptions!T24="","",Assumptions!T24) | U5: =IF(Assumptions!U24="","",Assumptions!U24) | W5: =IF(Assumptions!W24="","",Assumptions!W24) | X5: =IF(Assumptions!X24="","",Assumptions!X24) | Y5: =IF(Assumptions!Y24="","",Assumptions!Y24) | Z5: =IF(Assumptions!Z24="","",Assumptions!Z24) | AA5: =IF(Assumptions!AA24="","",Assumptions!AA24) | AB5: =IF(Assumptions!AB24="","",Assumptions!AB24)
A6: Pure benzene market average (RMB/t) | C6: 5025.66 | D6: 3929 | E6: 7109 | F6: 8125 | G6: 7250 | H6: 8300 | I6: 6254 | J6: 8241 | L6: 8442 | N6: 7438 | P6: 5905 | R6: 6416 | S6: =IF(Assumptions!S25="","",Assumptions!S25) | T6: =IF(Assumptions!T25="","",Assumptions!T25) | U6: =IF(Assumptions!U25="","",Assumptions!U25) | W6: =IF(Assumptions!W25="","",Assumptions!W25) | X6: =IF(Assumptions!X25="","",Assumptions!X25) | Y6: =IF(Assumptions!Y25="","",Assumptions!Y25) | Z6: =IF(Assumptions!Z25="","",Assumptions!Z25) | AA6: =IF(Assumptions!AA25="","",Assumptions!AA25) | AB6: =IF(Assumptions!AB25="","",Assumptions!AB25)
A7: PMDI − 0.77 × benzene rough spread (RMB/t) | B7: =IF(OR(B5="",B6=""),"",B5-0.77*B6) | C7: =IF(OR(C5="",C6=""),"",C5-0.77*C6) | D7: =IF(OR(D5="",D6=""),"",D5-0.77*D6) | E7: =IF(OR(E5="",E6=""),"",E5-0.77*E6) | F7: =IF(OR(F5="",F6=""),"",F5-0.77*F6) | G7: =IF(OR(G5="",G6=""),"",G5-0.77*G6) -> 10417.5 | H7: =IF(OR(H5="",H6=""),"",H5-0.77*H6) -> 10609 | I7: =IF(OR(I5="",I6=""),"",I5-0.77*I6) -> 11384.42 | ... AB7: =IF(OR(AB5="",AB6=""),"",AB5-0.77*AB6)
A8: Disclosure / formula boundary | B8: Company filing period average | C8: Company filing period average | D8: Company filing period average | E8: Company filing period average | F8: Company filing period average | G8: Company filing period average | H8: Company filing period average | I8: Company filing period average | J8: Company filing period average | K8: Company filing period average | L8: Company filing period average | M8: Company filing period average | N8: Company filing period average | O8: Company filing period average | P8: Company filing period average | Q8: Company filing period average | R8: Company filing period average | S8: Forecast assumption passthrough | T8: Forecast assumption passthrough | U8: Forecast assumption passthrough | V8: Q2 period average not directly derivable from H1 and Q1 disclosed averages. | W8: Forecast assumption passthrough | X8: Forecast assumption passthrough | Y8: Forecast assumption passthrough | Z8: Forecast assumption passthrough | AA8: Forecast assumption passthrough | AB8: Forecast assumption passthrough

Sheet Volume-Price
A1: Volume-Price
A2: Product-series revenue and volume from filings; apparent ASP uses revenue / disclosed volume.
A4: RMB mm unless stated | B4: 2018A | C4: 2019A | D4: 2020A | E4: 2021A | F4: 2022A | G4: 2023A | H4: 2024A | I4: 2025A | J4: 2024Q1A | K4: 2024Q2A | L4: 2024Q3A | M4: 2024Q4A | N4: 2025Q1A | O4: 2025Q2A | P4: 2025Q3A | Q4: 2025Q4A | R4: 2026Q1A | S4: 2026E | T4: 2027E | U4: 2028E | V4: 2026Q2A | W4: 2026Q3E | X4: 2026Q4E | Y4: 2027Q1E | Z4: 2027Q2E | AA4: 2027Q3E | AB4: 2027Q4E
A5: 聚氨酯系列
A6: Disclosed sales volume (10kt; includes internal use) | B6: 188.7114 | C6: 261.9603 | D6: 288.4384 | E6: 389 | F6: 418 | G6: 489 | H6: 564 | I6: 631 | J6: 131 | K6: 138 | L6: 141 | M6: 154 | N6: 145 | O6: 158 | P6: 155 | Q6: 173 | R6: 165 | S6: =IF(OR(I6="",S10=""),"",I6*(1+S10)) | T6: =IF(OR(S6="",T10=""),"",S6*(1+T10)) | U6: =IF(OR(T6="",U10=""),"",T6*(1+U10)) | V6: 161 | W6: =IF(OR(V6="",W10=""),"",V6*(1+W10)) | X6: =IF(OR(W6="",X10=""),"",W6*(1+X10)) | Y6: =IF(OR(X6="",Y10=""),"",X6*(1+Y10)) | Z6: =IF(OR(Y6="",Z10=""),"",Y6*(1+Z10)) | AA6: =IF(OR(Z6="",AA10=""),"",Z6*(1+AA10)) | AB6: =IF(OR(AA6="",AB10=""),"",AA6*(1+AB10))
A7: External sales volume (10kt; not disclosed)
A8: Reported product-series revenue | B8: 30951.892 | C8: 31858.132 | D8: 34416.866 | E8: 60492.225 | F8: 62895.628 | G8: 67386.16 | H8: 75844.15 | I8: 75058.224 | J8: 17501.79 | K8: 17953.55 | L8: 18790.05 | M8: 21598.76 | N8: 18427.05 | O8: 18460.74 | P8: 18254.82 | Q8: 19915.614 | R8: 19294.3 | V8: 25662.294
A9: Apparent ASP (RMB/t) | B9: =IFERROR(IF(OR(B6="",B6=0,B8=""),"",B8/B6*100),"") -> 16401.708 | C9: =IFERROR(IF(OR(C6="",C6=0,C8=""),"",C8/C6*100),"") -> 12161.435 | D9: =IFERROR(IF(OR(D6="",D6=0,D8=""),"",D8/D6*100),"") -> 11932.137 | E9: =IFERROR(IF(OR(E6="",E6=0,E8=""),"",E8/E6*100),"") -> 15550.7 | F9: =IFERROR(IF(OR(F6="",F6=0,F8=""),"",F8/F6*100),"") -> 15046.801 | G9: =IFERROR(IF(OR(G6="",G6=0,G8=""),"",G8/G6*100),"") -> 13780.401 | H9: =IFERROR(IF(OR(H6="",H6=0,H8=""),"",H8/H6*100),"") -> 13447.544 | I9: =IFERROR(IF(OR(I6="",I6=0,I8=""),"",I8/I6*100),"") -> 11895.123 | ... R9: =IFERROR(IF(OR(R6="",R6=0,R8=""),"",R8/R6*100),"") -> 11693.515 | S9: =IF(OR(I9="",S11=""),"",I9*(1+S11)) | T9: =IF(OR(S9="",T11=""),"",S9*(1+T11)) | U9: =IF(OR(T9="",U11=""),"",T9*(1+U11)) | V9: =IFERROR(IF(OR(V6="",V6=0,V8=""),"",V8/V6*100),"") -> 15939.313 | W9: =IF(OR(V9="",W11=""),"",V9*(1+W11)) | X9: =IF(OR(W9="",X11=""),"",W9*(1+X11)) | Y9: =IF(OR(X9="",Y11=""),"",X9*(1+Y11)) | Z9: =IF(OR(Y9="",Z11=""),"",Y9*(1+Z11)) | AA9: =IF(OR(Z9="",AA11=""),"",Z9*(1+AA11)) | AB9: =IF(OR(AA9="",AB11=""),"",AA9*(1+AB11))
A10: Volume growth | C10: =IFERROR(IF(OR(B6="",B6=0,C6=""),"",C6/B6-1),"") -> 0.38815302 | D10: =IFERROR(IF(OR(C6="",C6=0,D6=""),"",D6/C6-1),"") -> 0.10107677 | E10: =IFERROR(IF(OR(D6="",D6=0,E6=""),"",E6/D6-1),"") -> 0.34864151 | F10: =IFERROR(IF(OR(E6="",E6=0,F6=""),"",F6/E6-1),"") -> 0.074550129 | G10: =IFERROR(IF(OR(F6="",F6=0,G6=""),"",G6/F6-1),"") -> 0.16985646 | H10: =IFERROR(IF(OR(G6="",G6=0,H6=""),"",H6/G6-1),"") -> 0.15337423 | I10: =IFERROR(IF(OR(H6="",H6=0,I6=""),"",I6/H6-1),"") -> 0.11879433 | K10: =IFERROR(IF(OR(J6="",J6=0,K6=""),"",K6/J6-1),"") -> 0.053435115 | L10: =IFERROR(IF(OR(K6="",K6=0,L6=""),"",L6/K6-1),"") -> 0.02173913 | M10: =IFERROR(IF(OR(L6="",L6=0,M6=""),"",M6/L6-1),"") -> 0.092198582 | N10: =IFERROR(IF(OR(M6="",M6=0,N6=""),"",N6/M6-1),"") -> -0.058441558 | O10: =IFERROR(IF(OR(N6="",N6=0,O6=""),"",O6/N6-1),"") -> 0.089655172 | P10: =IFERROR(IF(OR(O6="",O6=0,P6=""),"",P6/O6-1),"") -> -0.018987342 | Q10: =IFERROR(IF(OR(P6="",P6=0,Q6=""),"",Q6/P6-1),"") -> 0.11612903 | R10: =IFERROR(IF(OR(Q6="",Q6=0,R6=""),"",R6/Q6-1),"") -> -0.046242775 | S10: =IF(Assumptions!S6="","",Assumptions!S6) | T10: =IF(Assumptions!T6="","",Assumptions!T6) | U10: =IF(Assumptions!U6="","",Assumptions!U6) | V10: =IFERROR(IF(OR(R6="",R6=0,V6=""),"",V6/R6-1),"") -> -0.024242424 | W10: =IF(Assumptions!W6="","",Assumptions!W6) | X10: =IF(Assumptions!X6="","",Assumptions!X6) | Y10: =IF(Assumptions!Y6="","",Assumptions!Y6) | Z10: =IF(Assumptions!Z6="","",Assumptions!Z6) | AA10: =IF(Assumptions!AA6="","",Assumptions!AA6) | AB10: =IF(Assumptions!AB6="","",Assumptions!AB6)
A11: Apparent ASP growth | C11: =IFERROR(IF(OR(B9="",B9=0,C9=""),"",C9/B9-1),"") -> -0.25852627 | D11: =IFERROR(IF(OR(C9="",C9=0,D9=""),"",D9/C9-1),"") -> -0.018854509 | E11: =IFERROR(IF(OR(D9="",D9=0,E9=""),"",E9/D9-1),"") -> 0.30326194 | F11: =IFERROR(IF(OR(E9="",E9=0,F9=""),"",F9/E9-1),"") -> -0.032403653 | G11: =IFERROR(IF(OR(F9="",F9=0,G9=""),"",G9/F9-1),"") -> -0.084164075 | H11: =IFERROR(IF(OR(G9="",G9=0,H9=""),"",H9/G9-1),"") -> -0.024154343 | I11: =IFERROR(IF(OR(H9="",H9=0,I9=""),"",I9/H9-1),"") -> -0.11544276 | K11: =IFERROR(IF(OR(J9="",J9=0,K9=""),"",K9/J9-1),"") -> -0.026221736 | L11: =IFERROR(IF(OR(K9="",K9=0,L9=""),"",L9/K9-1),"") -> 0.024324532 | M11: =IFERROR(IF(OR(L9="",L9=0,M9=""),"",M9/L9-1),"") -> 0.052444678 | N11: =IFERROR(IF(OR(M9="",M9=0,N9=""),"",N9/M9-1),"") -> -0.093892526 | O11: =IFERROR(IF(OR(N9="",N9=0,O9=""),"",O9/N9-1),"") -> -0.08060062 | P11: =IFERROR(IF(OR(O9="",O9=0,P9=""),"",P9/O9-1),"") -> 0.0079844631 | Q11: =IFERROR(IF(OR(P9="",P9=0,Q9=""),"",Q9/P9-1),"") -> -0.0225338 | R11: =IFERROR(IF(OR(Q9="",Q9=0,R9=""),"",R9/Q9-1),"") -> 0.0157749 | S11: =IF(Assumptions!S7="","",Assumptions!S7) | T11: =IF(Assumptions!T7="","",Assumptions!T7) | U11: =IF(Assumptions!U7="","",Assumptions!U7) | V11: =IFERROR(IF(OR(R9="",R9=0,V9=""),"",V9/R9-1),"") -> 0.36308995 | W11: =IF(Assumptions!W7="","",Assumptions!W7) | X11: =IF(Assumptions!X7="","",Assumptions!X7) | Y11: =IF(Assumptions!Y7="","",Assumptions!Y7) | Z11: =IF(Assumptions!Z7="","",Assumptions!Z7) | AA11: =IF(Assumptions!AA7="","",Assumptions!AA7) | AB11: =IF(Assumptions!AB7="","",Assumptions!AB7)
A12: Modelled revenue | B12: =IF(B8="","",B8) -> 30951.892 | C12: =IF(C8="","",C8) -> 31858.132 | D12: =IF(D8="","",D8) -> 34416.866 | E12: =IF(E8="","",E8) -> 60492.225 | F12: =IF(F8="","",F8) -> 62895.628 | G12: =IF(G8="","",G8) -> 67386.16 | H12: =IF(H8="","",H8) -> 75844.15 | I12: =IF(I8="","",I8) -> 75058.224 | ... R12: =IF(R8="","",R8) -> 19294.3 | S12: =IF(OR(S6="",S9=""),"",S6*S9/100) | T12: =IF(OR(T6="",T9=""),"",T6*T9/100) | U12: =IF(OR(U6="",U9=""),"",U6*U9/100) | V12: =IF(V8="","",V8) -> 25662.294 | W12: =IF(OR(W6="",W9=""),"",W6*W9/100) | X12: =IF(OR(X6="",X9=""),"",X6*X9/100) | Y12: =IF(OR(Y6="",Y9=""),"",Y6*Y9/100) | Z12: =IF(OR(Z6="",Z9=""),"",Z6*Z9/100) | AA12: =IF(OR(AA6="",AA9=""),"",AA6*AA9/100) | AB12: =IF(OR(AB6="",AB9=""),"",AB6*AB9/100)
A15: 石化系列
A16: Disclosed sales volume (10kt; includes internal use) | B16: 151.4707 | C16: 197.8362 | D16: 188.4886 | E16: 390 | F16: 454 | G16: 472 | H16: 547 | I16: 633 | J16: 134 | K16: 141 | L16: 132 | M16: 140 | N16: 133 | O16: 152 | P16: 175 | Q16: 173 | R16: 166 | S16: =IF(OR(I16="",S20=""),"",I16*(1+S20)) | T16: =IF(OR(S16="",T20=""),"",S16*(1+T20)) | U16: =IF(OR(T16="",U20=""),"",T16*(1+U20)) | V16: 173 | W16: =IF(OR(V16="",W20=""),"",V16*(1+W20)) | X16: =IF(OR(W16="",X20=""),"",W16*(1+X20)) | Y16: =IF(OR(X16="",Y20=""),"",X16*(1+Y20)) | Z16: =IF(OR(Y16="",Z20=""),"",Y16*(1+Z20)) | AA16: =IF(OR(Z16="",AA20=""),"",Z16*(1+AA20)) | AB16: =IF(OR(AA16="",AB20=""),"",AA16*(1+AB20))
A17: External sales volume (10kt; not disclosed)
A18: Reported product-series revenue | B18: 18907.546 | C18: 20102.036 | D18: 23084.987 | E18: 61409.365 | F18: 69635.164 | G18: 69327.924 | H18: 72518.272 | I18: 84203.81 | J18: 18513.68 | K18: 21061.08 | L18: 22403.04 | M18: 10540.472 | N18: 16320.12 | O18: 18613.44 | P18: 24385.72 | Q18: 24884.53 | R18: 20505.86 | V18: 27231.705
A19: Apparent ASP (RMB/t) | B19: =IFERROR(IF(OR(B16="",B16=0,B18=""),"",B18/B16*100),"") -> 12482.642 | C19: =IFERROR(IF(OR(C16="",C16=0,C18=""),"",C18/C16*100),"") -> 10160.949 | D19: =IFERROR(IF(OR(D16="",D16=0,D18=""),"",D18/D16*100),"") -> 12247.418 | E19: =IFERROR(IF(OR(E16="",E16=0,E18=""),"",E18/E16*100),"") -> 15745.991 | F19: =IFERROR(IF(OR(F16="",F16=0,F18=""),"",F18/F16*100),"") -> 15338.142 | G19: =IFERROR(IF(OR(G16="",G16=0,G18=""),"",G18/G16*100),"") -> 14688.12 | H19: =IFERROR(IF(OR(H16="",H16=0,H18=""),"",H18/H16*100),"") -> 13257.454 | I19: =IFERROR(IF(OR(I16="",I16=0,I18=""),"",I18/I16*100),"") -> 13302.34 | ... R19: =IFERROR(IF(OR(R16="",R16=0,R18=""),"",R18/R16*100),"") -> 12352.928 | S19: =IF(OR(I19="",S21=""),"",I19*(1+S21)) | T19: =IF(OR(S19="",T21=""),"",S19*(1+T21)) | U19: =IF(OR(T19="",U21=""),"",T19*(1+U21)) | V19: =IFERROR(IF(OR(V16="",V16=0,V18=""),"",V18/V16*100),"") -> 15740.87 | W19: =IF(OR(V19="",W21=""),"",V19*(1+W21)) | X19: =IF(OR(W19="",X21=""),"",W19*(1+X21)) | Y19: =IF(OR(X19="",Y21=""),"",X19*(1+Y21)) | Z19: =IF(OR(Y19="",Z21=""),"",Y19*(1+Z21)) | AA19: =IF(OR(Z19="",AA21=""),"",Z19*(1+AA21)) | AB19: =IF(OR(AA19="",AB21=""),"",AA19*(1+AB21))
A20: Volume growth | C20: =IFERROR(IF(OR(B16="",B16=0,C16=""),"",C16/B16-1),"") -> 0.3061021 | D20: =IFERROR(IF(OR(C16="",C16=0,D16=""),"",D16/C16-1),"") -> -0.047249189 | E20: =IFERROR(IF(OR(D16="",D16=0,E16=""),"",E16/D16-1),"") -> 1.0690907 | F20: =IFERROR(IF(OR(E16="",E16=0,F16=""),"",F16/E16-1),"") -> 0.16410256 | G20: =IFERROR(IF(OR(F16="",F16=0,G16=""),"",G16/F16-1),"") -> 0.039647577 | H20: =IFERROR(IF(OR(G16="",G16=0,H16=""),"",H16/G16-1),"") -> 0.15889831 | I20: =IFERROR(IF(OR(H16="",H16=0,I16=""),"",I16/H16-1),"") -> 0.15722121 | K20: =IFERROR(IF(OR(J16="",J16=0,K16=""),"",K16/J16-1),"") -> 0.052238806 | L20: =IFERROR(IF(OR(K16="",K16=0,L16=""),"",L16/K16-1),"") -> -0.063829787 | M20: =IFERROR(IF(OR(L16="",L16=0,M16=""),"",M16/L16-1),"") -> 0.060606061 | N20: =IFERROR(IF(OR(M16="",M16=0,N16=""),"",N16/M16-1),"") -> -0.05 | O20: =IFERROR(IF(OR(N16="",N16=0,O16=""),"",O16/N16-1),"") -> 0.14285714 | P20: =IFERROR(IF(OR(O16="",O16=0,P16=""),"",P16/O16-1),"") -> 0.15131579 | Q20: =IFERROR(IF(OR(P16="",P16=0,Q16=""),"",Q16/P16-1),"") -> -0.011428571 | R20: =IFERROR(IF(OR(Q16="",Q16=0,R16=""),"",R16/Q16-1),"") -> -0.040462428 | S20: =IF(Assumptions!S12="","",Assumptions!S12) | T20: =IF(Assumptions!T12="","",Assumptions!T12) | U20: =IF(Assumptions!U12="","",Assumptions!U12) | V20: =IFERROR(IF(OR(R16="",R16=0,V16=""),"",V16/R16-1),"") -> 0.042168675 | W20: =IF(Assumptions!W12="","",Assumptions!W12) | X20: =IF(Assumptions!X12="","",Assumptions!X12) | Y20: =IF(Assumptions!Y12="","",Assumptions!Y12) | Z20: =IF(Assumptions!Z12="","",Assumptions!Z12) | AA20: =IF(Assumptions!AA12="","",Assumptions!AA12) | AB20: =IF(Assumptions!AB12="","",Assumptions!AB12)
A21: Apparent ASP growth | C21: =IFERROR(IF(OR(B19="",B19=0,C19=""),"",C19/B19-1),"") -> -0.18599373 | D21: =IFERROR(IF(OR(C19="",C19=0,D19=""),"",D19/C19-1),"") -> 0.20534193 | E21: =IFERROR(IF(OR(D19="",D19=0,E19=""),"",E19/D19-1),"") -> 0.285658 | F21: =IFERROR(IF(OR(E19="",E19=0,F19=""),"",F19/E19-1),"") -> -0.025901785 | G21: =IFERROR(IF(OR(F19="",F19=0,G19=""),"",G19/F19-1),"") -> -0.042379467 | H21: =IFERROR(IF(OR(G19="",G19=0,H19=""),"",H19/G19-1),"") -> -0.097402923 | I21: =IFERROR(IF(OR(H19="",H19=0,I19=""),"",I19/H19-1),"") -> 0.0033857178 | K21: =IFERROR(IF(OR(J19="",J19=0,K19=""),"",K19/J19-1),"") -> 0.081119176 | L21: =IFERROR(IF(OR(K19="",K19=0,L19=""),"",L19/K19-1),"") -> 0.13624373 | M21: =IFERROR(IF(OR(L19="",L19=0,M19=""),"",M19/L19-1),"") -> -0.55639238 | N21: =IFERROR(IF(OR(M19="",M19=0,N19=""),"",N19/M19-1),"") -> 0.62982016 | O21: =IFERROR(IF(OR(N19="",N19=0,O19=""),"",O19/N19-1),"") -> -0.0020441026 | P21: =IFERROR(IF(OR(O19="",O19=0,P19=""),"",P19/O19-1),"") -> 0.1379272 | Q21: =IFERROR(IF(OR(P19="",P19=0,Q19=""),"",Q19/P19-1),"") -> 0.032252192 | R21: =IFERROR(IF(OR(Q19="",Q19=0,R19=""),"",R19/Q19-1),"") -> -0.14121084 | S21: =IF(Assumptions!S13="","",Assumptions!S13) | T21: =IF(Assumptions!T13="","",Assumptions!T13) | U21: =IF(Assumptions!U13="","",Assumptions!U13) | V21: =IFERROR(IF(OR(R19="",R19=0,V19=""),"",V19/R19-1),"") -> 0.27426227 | W21: =IF(Assumptions!W13="","",Assumptions!W13) | X21: =IF(Assumptions!X13="","",Assumptions!X13) | Y21: =IF(Assumptions!Y13="","",Assumptions!Y13) | Z21: =IF(Assumptions!Z13="","",Assumptions!Z13) | AA21: =IF(Assumptions!AA13="","",Assumptions!AA13) | AB21: =IF(Assumptions!AB13="","",Assumptions!AB13)
A22: Modelled revenue | B22: =IF(B18="","",B18) -> 18907.546 | C22: =IF(C18="","",C18) -> 20102.036 | D22: =IF(D18="","",D18) -> 23084.987 | E22: =IF(E18="","",E18) -> 61409.365 | F22: =IF(F18="","",F18) -> 69635.164 | G22: =IF(G18="","",G18) -> 69327.924 | H22: =IF(H18="","",H18) -> 72518.272 | I22: =IF(I18="","",I18) -> 84203.81 | ... R22: =IF(R18="","",R18) -> 20505.86 | S22: =IF(OR(S16="",S19=""),"",S16*S19/100) | T22: =IF(OR(T16="",T19=""),"",T16*T19/100) | U22: =IF(OR(U16="",U19=""),"",U16*U19/100) | V22: =IF(V18="","",V18) -> 27231.705 | W22: =IF(OR(W16="",W19=""),"",W16*W19/100) | X22: =IF(OR(X16="",X19=""),"",X16*X19/100) | Y22: =IF(OR(Y16="",Y19=""),"",Y16*Y19/100) | Z22: =IF(OR(Z16="",Z19=""),"",Z16*Z19/100) | AA22: =IF(OR(AA16="",AA19=""),"",AA16*AA19/100) | AB22: =IF(OR(AB16="",AB19=""),"",AB16*AB19/100)
A25: 精细化学品及新材料系列
A26: Disclosed sales volume (10kt; includes internal use) | B26: 32.1668 | C26: 41.467 | D26: 55.4944 | E26: 76 | F26: 95 | G26: 159 | H26: 203 | I26: 256 | J26: 44 | K26: 48 | L26: 50 | M26: 61 | N26: 54 | O26: 65 | P26: 65 | Q26: 72 | R26: 73 | S26: =IF(OR(I26="",S30=""),"",I26*(1+S30)) | T26: =IF(OR(S26="",T30=""),"",S26*(1+T30)) | U26: =IF(OR(T26="",U30=""),"",T26*(1+U30)) | V26: 75 | W26: =IF(OR(V26="",W30=""),"",V26*(1+W30)) | X26: =IF(OR(W26="",X30=""),"",W26*(1+X30)) | Y26: =IF(OR(X26="",Y30=""),"",X26*(1+Y30)) | Z26: =IF(OR(Y26="",Z30=""),"",Y26*(1+Z30)) | AA26: =IF(OR(Z26="",AA30=""),"",Z26*(1+AA30)) | AB26: =IF(OR(AA26="",AB30=""),"",AA26*(1+AB30))
A27: External sales volume (10kt; not disclosed)
A28: Reported product-series revenue | B28: 5702.9624 | C28: 7087.781 | D28: 7947.8577 | E28: 15463.788 | F28: 20124.158 | G28: 23836.062 | H28: 28273.081 | I28: 33189.13 | J28: 6105.04 | K28: 6873.64 | L28: 7020.42 | M28: 8273.9805 | N28: 7370.45 | O28: 8257.62 | P28: 8183.38 | Q28: 9377.6796 | R28: 10344.79 | V28: 12202.909
A29: Apparent ASP (RMB/t) | B29: =IFERROR(IF(OR(B26="",B26=0,B28=""),"",B28/B26*100),"") -> 17729.343 | C29: =IFERROR(IF(OR(C26="",C26=0,C28=""),"",C28/C26*100),"") -> 17092.582 | D29: =IFERROR(IF(OR(D26="",D26=0,D28=""),"",D28/D26*100),"") -> 14321.909 | E29: =IFERROR(IF(OR(E26="",E26=0,E28=""),"",E28/E26*100),"") -> 20347.09 | F29: =IFERROR(IF(OR(F26="",F26=0,F28=""),"",F28/F26*100),"") -> 21183.325 | G29: =IFERROR(IF(OR(G26="",G26=0,G28=""),"",G28/G26*100),"") -> 14991.234 | H29: =IFERROR(IF(OR(H26="",H26=0,H28=""),"",H28/H26*100),"") -> 13927.626 | I29: =IFERROR(IF(OR(I26="",I26=0,I28=""),"",I28/I26*100),"") -> 12964.504 | ... R29: =IFERROR(IF(OR(R26="",R26=0,R28=""),"",R28/R26*100),"") -> 14170.945 | S29: =IF(OR(I29="",S31=""),"",I29*(1+S31)) | T29: =IF(OR(S29="",T31=""),"",S29*(1+T31)) | U29: =IF(OR(T29="",U31=""),"",T29*(1+U31)) | V29: =IFERROR(IF(OR(V26="",V26=0,V28=""),"",V28/V26*100),"") -> 16270.546 | W29: =IF(OR(V29="",W31=""),"",V29*(1+W31)) | X29: =IF(OR(W29="",X31=""),"",W29*(1+X31)) | Y29: =IF(OR(X29="",Y31=""),"",X29*(1+Y31)) | Z29: =IF(OR(Y29="",Z31=""),"",Y29*(1+Z31)) | AA29: =IF(OR(Z29="",AA31=""),"",Z29*(1+AA31)) | AB29: =IF(OR(AA29="",AB31=""),"",AA29*(1+AB31))
A30: Volume growth | C30: =IFERROR(IF(OR(B26="",B26=0,C26=""),"",C26/B26-1),"") -> 0.28912419 | D30: =IFERROR(IF(OR(C26="",C26=0,D26=""),"",D26/C26-1),"") -> 0.33827863 | E30: =IFERROR(IF(OR(D26="",D26=0,E26=""),"",E26/D26-1),"") -> 0.36950755 | F30: =IFERROR(IF(OR(E26="",E26=0,F26=""),"",F26/E26-1),"") -> 0.25 | G30: =IFERROR(IF(OR(F26="",F26=0,G26=""),"",G26/F26-1),"") -> 0.67368421 | H30: =IFERROR(IF(OR(G26="",G26=0,H26=""),"",H26/G26-1),"") -> 0.27672956 | I30: =IFERROR(IF(OR(H26="",H26=0,I26=""),"",I26/H26-1),"") -> 0.26108374 | K30: =IFERROR(IF(OR(J26="",J26=0,K26=""),"",K26/J26-1),"") -> 0.090909091 | L30: =IFERROR(IF(OR(K26="",K26=0,L26=""),"",L26/K26-1),"") -> 0.041666667 | M30: =IFERROR(IF(OR(L26="",L26=0,M26=""),"",M26/L26-1),"") -> 0.22 | N30: =IFERROR(IF(OR(M26="",M26=0,N26=""),"",N26/M26-1),"") -> -0.1147541 | O30: =IFERROR(IF(OR(N26="",N26=0,O26=""),"",O26/N26-1),"") -> 0.2037037 | P30: =IFERROR(IF(OR(O26="",O26=0,P26=""),"",P26/O26-1),"") -> 0 | Q30: =IFERROR(IF(OR(P26="",P26=0,Q26=""),"",Q26/P26-1),"") -> 0.10769231 | R30: =IFERROR(IF(OR(Q26="",Q26=0,R26=""),"",R26/Q26-1),"") -> 0.013888889 | S30: =IF(Assumptions!S18="","",Assumptions!S18) | T30: =IF(Assumptions!T18="","",Assumptions!T18) | U30: =IF(Assumptions!U18="","",Assumptions!U18) | V30: =IFERROR(IF(OR(R26="",R26=0,V26=""),"",V26/R26-1),"") -> 0.02739726 | W30: =IF(Assumptions!W18="","",Assumptions!W18) | X30: =IF(Assumptions!X18="","",Assumptions!X18) | Y30: =IF(Assumptions!Y18="","",Assumptions!Y18) | Z30: =IF(Assumptions!Z18="","",Assumptions!Z18) | AA30: =IF(Assumptions!AA18="","",Assumptions!AA18) | AB30: =IF(Assumptions!AB18="","",Assumptions!AB18)
A31: Apparent ASP growth | C31: =IFERROR(IF(OR(B29="",B29=0,C29=""),"",C29/B29-1),"") -> -0.035915662 | D31: =IFERROR(IF(OR(C29="",C29=0,D29=""),"",D29/C29-1),"") -> -0.16209796 | E31: =IFERROR(IF(OR(D29="",D29=0,E29=""),"",E29/D29-1),"") -> 0.42069674 | F31: =IFERROR(IF(OR(E29="",E29=0,F29=""),"",F29/E29-1),"") -> 0.041098487 | G31: =IFERROR(IF(OR(F29="",F29=0,G29=""),"",G29/F29-1),"") -> -0.29230966 | H31: =IFERROR(IF(OR(G29="",G29=0,H29=""),"",H29/G29-1),"") -> -0.070948689 | I31: =IFERROR(IF(OR(H29="",H29=0,I29=""),"",I29/H29-1),"") -> -0.069151922 | K31: =IFERROR(IF(OR(J29="",J29=0,K29=""),"",K29/J29-1),"") -> 0.032071316 | L31: =IFERROR(IF(OR(K29="",K29=0,L29=""),"",L29/K29-1),"") -> -0.019500119 | M31: =IFERROR(IF(OR(L29="",L29=0,M29=""),"",M29/L29-1),"") -> -0.033967878 | N31: =IFERROR(IF(OR(M29="",M29=0,N29=""),"",N29/M29-1),"") -> 0.006272459 | O31: =IFERROR(IF(OR(N29="",N29=0,O29=""),"",O29/N29-1),"") -> -0.069232324 | P31: =IFERROR(IF(OR(O29="",O29=0,P29=""),"",P29/O29-1),"") -> -0.0089904839 | Q31: =IFERROR(IF(OR(P29="",P29=0,Q29=""),"",Q29/P29-1),"") -> 0.03453106 | R31: =IFERROR(IF(OR(Q29="",Q29=0,R29=""),"",R29/Q29-1),"") -> 0.088017605 | S31: =IF(Assumptions!S19="","",Assumptions!S19) | T31: =IF(Assumptions!T19="","",Assumptions!T19) | U31: =IF(Assumptions!U19="","",Assumptions!U19) | V31: =IFERROR(IF(OR(R29="",R29=0,V29=""),"",V29/R29-1),"") -> 0.14816235 | W31: =IF(Assumptions!W19="","",Assumptions!W19) | X31: =IF(Assumptions!X19="","",Assumptions!X19) | Y31: =IF(Assumptions!Y19="","",Assumptions!Y19) | Z31: =IF(Assumptions!Z19="","",Assumptions!Z19) | AA31: =IF(Assumptions!AA19="","",Assumptions!AA19) | AB31: =IF(Assumptions!AB19="","",Assumptions!AB19)
A32: Modelled revenue | B32: =IF(B28="","",B28) -> 5702.9624 | C32: =IF(C28="","",C28) -> 7087.781 | D32: =IF(D28="","",D28) -> 7947.8577 | E32: =IF(E28="","",E28) -> 15463.788 | F32: =IF(F28="","",F28) -> 20124.158 | G32: =IF(G28="","",G28) -> 23836.062 | H32: =IF(H28="","",H28) -> 28273.081 | I32: =IF(I28="","",I28) -> 33189.13 | ... R32: =IF(R28="","",R28) -> 10344.79 | S32: =IF(OR(S26="",S29=""),"",S26*S29/100) | T32: =IF(OR(T26="",T29=""),"",T26*T29/100) | U32: =IF(OR(U26="",U29=""),"",U26*U29/100) | V32: =IF(V28="","",V28) -> 12202.909 | W32: =IF(OR(W26="",W29=""),"",W26*W29/100) | X32: =IF(OR(X26="",X29=""),"",X26*X29/100) | Y32: =IF(OR(Y26="",Y29=""),"",Y26*Y29/100) | Z32: =IF(OR(Z26="",Z29=""),"",Z26*Z29/100) | AA32: =IF(OR(AA26="",AA29=""),"",AA26*AA29/100) | AB32: =IF(OR(AB26="",AB29=""),"",AB26*AB29/100)

Sheet Cost Bridge
A1: Cost Bridge
A2: Annual segment costs and raw-material shares are filing actuals; quarterly segment costs are intentionally blank.
A4: RMB mm unless stated | B4: 2018A | C4: 2019A | D4: 2020A | E4: 2021A | F4: 2022A | G4: 2023A | H4: 2024A | I4: 2025A | J4: 2024Q1A | K4: 2024Q2A | L4: 2024Q3A | M4: 2024Q4A | N4: 2025Q1A | O4: 2025Q2A | P4: 2025Q3A | Q4: 2025Q4A | R4: 2026Q1A | S4: 2026E | T4: 2027E | U4: 2028E | V4: 2026Q2A | W4: 2026Q3E | X4: 2026Q4E | Y4: 2027Q1E | Z4: 2027Q2E | AA4: 2027Q3E | AB4: 2027Q4E
A5: 聚氨酯系列
A6: Disclosed sales volume (10kt) | B6: ='Volume-Price'!B6 -> 188.7114 | C6: ='Volume-Price'!C6 -> 261.9603 | D6: ='Volume-Price'!D6 -> 288.4384 | E6: ='Volume-Price'!E6 -> 389 | F6: ='Volume-Price'!F6 -> 418 | G6: ='Volume-Price'!G6 -> 489 | H6: ='Volume-Price'!H6 -> 564 | I6: ='Volume-Price'!I6 -> 631 | ... AB6: ='Volume-Price'!AB6
A7: Reported product-series cost | B7: 15384.314 | C7: 18687.947 | D7: 19441.716 | E7: 39277.435 | F7: 47518.326 | G7: 48725.3 | H7: 56009.192 | I7: 54880.846
A8: Unit cost proxy (RMB/t) | B8: =IFERROR(IF(OR(B6="",B6=0,B7=""),"",B7/B6*100),"") -> 8152.2971 | C8: =IFERROR(IF(OR(C6="",C6=0,C7=""),"",C7/C6*100),"") -> 7133.8853 | D8: =IFERROR(IF(OR(D6="",D6=0,D7=""),"",D7/D6*100),"") -> 6740.3355 | E8: =IFERROR(IF(OR(E6="",E6=0,E7=""),"",E7/E6*100),"") -> 10097.027 | F8: =IFERROR(IF(OR(F6="",F6=0,F7=""),"",F7/F6*100),"") -> 11368.02 | G8: =IFERROR(IF(OR(G6="",G6=0,G7=""),"",G7/G6*100),"") -> 9964.2741 | H8: =IFERROR(IF(OR(H6="",H6=0,H7=""),"",H7/H6*100),"") -> 9930.7078 | I8: =IFERROR(IF(OR(I6="",I6=0,I7=""),"",I7/I6*100),"") -> 8697.4399 | ... AB8: =IFERROR(IF(OR(AB6="",AB6=0,AB7=""),"",AB7/AB6*100),"")
A9: Raw-material share of product-series cost | B9: 0.7223 | C9: 0.6895 | D9: 0.6882 | E9: 0.745 | F9: 0.7523 | G9: 0.7456 | H9: 0.7435 | I9: 0.7368 | S9: =IF(Assumptions!S8="","",Assumptions!S8) | T9: =IF(Assumptions!T8="","",Assumptions!T8) | U9: =IF(Assumptions!U8="","",Assumptions!U8) | V9: =IF(Assumptions!V8="","",Assumptions!V8) | W9: =IF(Assumptions!W8="","",Assumptions!W8) | X9: =IF(Assumptions!X8="","",Assumptions!X8) | Y9: =IF(Assumptions!Y8="","",Assumptions!Y8) | Z9: =IF(Assumptions!Z8="","",Assumptions!Z8) | ... AB9: =IF(Assumptions!AB8="","",Assumptions!AB8)
A10: Raw price index (2025A benzene = 1.00x) | B10: =IFERROR(IF(OR('Price Inputs'!B$6="",'Price Inputs'!$I$6=""),"",'Price Inputs'!B$6/'Price Inputs'!$I$6),"") | C10: =IFERROR(IF(OR('Price Inputs'!C$6="",'Price Inputs'!$I$6=""),"",'Price Inputs'!C$6/'Price Inputs'!$I$6),"") -> 0.8035913 | D10: =IFERROR(IF(OR('Price Inputs'!D$6="",'Price Inputs'!$I$6=""),"",'Price Inputs'!D$6/'Price Inputs'!$I$6),"") -> 0.62823793 | E10: =IFERROR(IF(OR('Price Inputs'!E$6="",'Price Inputs'!$I$6=""),"",'Price Inputs'!E$6/'Price Inputs'!$I$6),"") -> 1.1367125 | F10: =IFERROR(IF(OR('Price Inputs'!F$6="",'Price Inputs'!$I$6=""),"",'Price Inputs'!F$6/'Price Inputs'!$I$6),"") -> 1.2991685 | G10: =IFERROR(IF(OR('Price Inputs'!G$6="",'Price Inputs'!$I$6=""),"",'Price Inputs'!G$6/'Price Inputs'!$I$6),"") -> 1.1592581 | H10: =IFERROR(IF(OR('Price Inputs'!H$6="",'Price Inputs'!$I$6=""),"",'Price Inputs'!H$6/'Price Inputs'!$I$6),"") -> 1.3271506 | I10: =IFERROR(IF(OR('Price Inputs'!I$6="",'Price Inputs'!$I$6=""),"",'Price Inputs'!I$6/'Price Inputs'!$I$6),"") -> 1 | ... U10: =IFERROR(IF(OR('Price Inputs'!U$6="",'Price Inputs'!$I$6=""),"",'Price Inputs'!U$6/'Price Inputs'!$I$6),"") | V10: ='Price Inputs'!V7 | W10: =IFERROR(IF(OR('Price Inputs'!W$6="",'Price Inputs'!$I$6=""),"",'Price Inputs'!W$6/'Price Inputs'!$I$6),"") | X10: =IFERROR(IF(OR('Price Inputs'!X$6="",'Price Inputs'!$I$6=""),"",'Price Inputs'!X$6/'Price Inputs'!$I$6),"") | Y10: =IFERROR(IF(OR('Price Inputs'!Y$6="",'Price Inputs'!$I$6=""),"",'Price Inputs'!Y$6/'Price Inputs'!$I$6),"") | Z10: =IFERROR(IF(OR('Price Inputs'!Z$6="",'Price Inputs'!$I$6=""),"",'Price Inputs'!Z$6/'Price Inputs'!$I$6),"") | AA10: =IFERROR(IF(OR('Price Inputs'!AA$6="",'Price Inputs'!$I$6=""),"",'Price Inputs'!AA$6/'Price Inputs'!$I$6),"") | AB10: =IFERROR(IF(OR('Price Inputs'!AB$6="",'Price Inputs'!$I$6=""),"",'Price Inputs'!AB$6/'Price Inputs'!$I$6),"")
A11: Non-raw cost index | B11: =IF(B8="","",1) -> 1 | C11: =IF(C8="","",1) -> 1 | D11: =IF(D8="","",1) -> 1 | E11: =IF(E8="","",1) -> 1 | F11: =IF(F8="","",1) -> 1 | G11: =IF(G8="","",1) -> 1 | H11: =IF(H8="","",1) -> 1 | I11: =IF(I8="","",1) -> 1 | ... R11: =IF(R8="","",1) | S11: =IF(Assumptions!S9="","",1*(1+Assumptions!S9)) | T11: =IF(Assumptions!T9="","",S11*(1+Assumptions!T9)) | U11: =IF(Assumptions!U9="","",T11*(1+Assumptions!U9)) | V11: =IF(V8="","",1) | W11: =IF(Assumptions!W9="","",V11*(1+Assumptions!W9)) | X11: =IF(Assumptions!X9="","",W11*(1+Assumptions!X9)) | Y11: =IF(Assumptions!Y9="","",X11*(1+Assumptions!Y9)) | Z11: =IF(Assumptions!Z9="","",Y11*(1+Assumptions!Z9)) | AA11: =IF(Assumptions!AA9="","",Z11*(1+Assumptions!AA9)) | AB11: =IF(Assumptions!AB9="","",AA11*(1+Assumptions!AB9))
A12: Forecast unit cost (RMB/t) | B12: =IF(B8="","",B8) -> 8152.2971 | C12: =IF(C8="","",C8) -> 7133.8853 | D12: =IF(D8="","",D8) -> 6740.3355 | E12: =IF(E8="","",E8) -> 10097.027 | F12: =IF(F8="","",F8) -> 11368.02 | G12: =IF(G8="","",G8) -> 9964.2741 | H12: =IF(H8="","",H8) -> 9930.7078 | I12: =IF(I8="","",I8) -> 8697.4399 | ... R12: =IF(R8="","",R8) | S12: =IF(OR($I$8="",S9="",S10="",S11=""),"",$I$8*(S9*S10+(1-S9)*S11)) | T12: =IF(OR($I$8="",T9="",T10="",T11=""),"",$I$8*(T9*T10+(1-T9)*T11)) | U12: =IF(OR($I$8="",U9="",U10="",U11=""),"",$I$8*(U9*U10+(1-U9)*U11)) | V12: =IF(V8="","",V8) | W12: =IF(OR($I$8="",W9="",W10="",W11=""),"",$I$8*(W9*W10+(1-W9)*W11)) | X12: =IF(OR($I$8="",X9="",X10="",X11=""),"",$I$8*(X9*X10+(1-X9)*X11)) | Y12: =IF(OR($I$8="",Y9="",Y10="",Y11=""),"",$I$8*(Y9*Y10+(1-Y9)*Y11)) | Z12: =IF(OR($I$8="",Z9="",Z10="",Z11=""),"",$I$8*(Z9*Z10+(1-Z9)*Z11)) | AA12: =IF(OR($I$8="",AA9="",AA10="",AA11=""),"",$I$8*(AA9*AA10+(1-AA9)*AA11)) | AB12: =IF(OR($I$8="",AB9="",AB10="",AB11=""),"",$I$8*(AB9*AB10+(1-AB9)*AB11))
A13: Modelled product-series cost | B13: =IF(B7="","",B7) -> 15384.314 | C13: =IF(C7="","",C7) -> 18687.947 | D13: =IF(D7="","",D7) -> 19441.716 | E13: =IF(E7="","",E7) -> 39277.435 | F13: =IF(F7="","",F7) -> 47518.326 | G13: =IF(G7="","",G7) -> 48725.3 | H13: =IF(H7="","",H7) -> 56009.192 | I13: =IF(I7="","",I7) -> 54880.846 | ... R13: =IF(R7="","",R7) | S13: =IF(OR(S6="",S12=""),"",S6*S12/100) | T13: =IF(OR(T6="",T12=""),"",T6*T12/100) | U13: =IF(OR(U6="",U12=""),"",U6*U12/100) | V13: =IF(V7="","",V7) | W13: =IF(OR(W6="",W12=""),"",W6*W12/100) | X13: =IF(OR(X6="",X12=""),"",X6*X12/100) | Y13: =IF(OR(Y6="",Y12=""),"",Y6*Y12/100) | Z13: =IF(OR(Z6="",Z12=""),"",Z6*Z12/100) | AA13: =IF(OR(AA6="",AA12=""),"",AA6*AA12/100) | AB13: =IF(OR(AB6="",AB12=""),"",AB6*AB12/100)
A16: 石化系列
A17: Disclosed sales volume (10kt) | B17: ='Volume-Price'!B16 -> 151.4707 | C17: ='Volume-Price'!C16 -> 197.8362 | D17: ='Volume-Price'!D16 -> 188.4886 | E17: ='Volume-Price'!E16 -> 390 | F17: ='Volume-Price'!F16 -> 454 | G17: ='Volume-Price'!G16 -> 472 | H17: ='Volume-Price'!H16 -> 547 | I17: ='Volume-Price'!I16 -> 633 | ... AB17: ='Volume-Price'!AB16
A18: Reported product-series cost | B18: 17021.133 | C18: 17859.814 | D18: 22102.639 | E18: 50916.478 | F18: 67032.076 | G18: 66891.14 | H18: 69965.5 | I18: 83718.342
A19: Unit cost proxy (RMB/t) | B19: =IFERROR(IF(OR(B17="",B17=0,B18=""),"",B18/B17*100),"") -> 11237.245 | C19: =IFERROR(IF(OR(C17="",C17=0,C18=""),"",C18/C17*100),"") -> 9027.5761 | D19: =IFERROR(IF(OR(D17="",D17=0,D18=""),"",D18/D17*100),"") -> 11726.247 | E19: =IFERROR(IF(OR(E17="",E17=0,E18=""),"",E18/E17*100),"") -> 13055.507 | F19: =IFERROR(IF(OR(F17="",F17=0,F18=""),"",F18/F17*100),"") -> 14764.774 | G19: =IFERROR(IF(OR(G17="",G17=0,G18=""),"",G18/G17*100),"") -> 14171.852 | H19: =IFERROR(IF(OR(H17="",H17=0,H18=""),"",H18/H17*100),"") -> 12790.768 | I19: =IFERROR(IF(OR(I17="",I17=0,I18=""),"",I18/I17*100),"") -> 13225.646 | ... AB19: =IFERROR(IF(OR(AB17="",AB17=0,AB18=""),"",AB18/AB17*100),"")
A20: Raw-material share of product-series cost | B20: 0.8414 | C20: 0.8257 | D20: 0.8595 | E20: 0.8727 | F20: 0.8795 | G20: 0.882 | H20: 0.8735 | I20: 0.8857 | S20: =IF(Assumptions!S14="","",Assumptions!S14) | T20: =IF(Assumptions!T14="","",Assumptions!T14) | U20: =IF(Assumptions!U14="","",Assumptions!U14) | V20: =IF(Assumptions!V14="","",Assumptions!V14) | W20: =IF(Assumptions!W14="","",Assumptions!W14) | X20: =IF(Assumptions!X14="","",Assumptions!X14) | Y20: =IF(Assumptions!Y14="","",Assumptions!Y14) | Z20: =IF(Assumptions!Z14="","",Assumptions!Z14) | ... AB20: =IF(Assumptions!AB14="","",Assumptions!AB14)
A21: Raw price index (2025A benzene = 1.00x) | B21: =IFERROR(IF(OR('Price Inputs'!B$6="",'Price Inputs'!$I$6=""),"",'Price Inputs'!B$6/'Price Inputs'!$I$6),"") | C21: =IFERROR(IF(OR('Price Inputs'!C$6="",'Price Inputs'!$I$6=""),"",'Price Inputs'!C$6/'Price Inputs'!$I$6),"") -> 0.8035913 | D21: =IFERROR(IF(OR('Price Inputs'!D$6="",'Price Inputs'!$I$6=""),"",'Price Inputs'!D$6/'Price Inputs'!$I$6),"") -> 0.62823793 | E21: =IFERROR(IF(OR('Price Inputs'!E$6="",'Price Inputs'!$I$6=""),"",'Price Inputs'!E$6/'Price Inputs'!$I$6),"") -> 1.1367125 | F21: =IFERROR(IF(OR('Price Inputs'!F$6="",'Price Inputs'!$I$6=""),"",'Price Inputs'!F$6/'Price Inputs'!$I$6),"") -> 1.2991685 | G21: =IFERROR(IF(OR('Price Inputs'!G$6="",'Price Inputs'!$I$6=""),"",'Price Inputs'!G$6/'Price Inputs'!$I$6),"") -> 1.1592581 | H21: =IFERROR(IF(OR('Price Inputs'!H$6="",'Price Inputs'!$I$6=""),"",'Price Inputs'!H$6/'Price Inputs'!$I$6),"") -> 1.3271506 | I21: =IFERROR(IF(OR('Price Inputs'!I$6="",'Price Inputs'!$I$6=""),"",'Price Inputs'!I$6/'Price Inputs'!$I$6),"") -> 1 | ... U21: =IFERROR(IF(OR('Price Inputs'!U$6="",'Price Inputs'!$I$6=""),"",'Price Inputs'!U$6/'Price Inputs'!$I$6),"") | V21: ='Price Inputs'!V7 | W21: =IFERROR(IF(OR('Price Inputs'!W$6="",'Price Inputs'!$I$6=""),"",'Price Inputs'!W$6/'Price Inputs'!$I$6),"") | X21: =IFERROR(IF(OR('Price Inputs'!X$6="",'Price Inputs'!$I$6=""),"",'Price Inputs'!X$6/'Price Inputs'!$I$6),"") | Y21: =IFERROR(IF(OR('Price Inputs'!Y$6="",'Price Inputs'!$I$6=""),"",'Price Inputs'!Y$6/'Price Inputs'!$I$6),"") | Z21: =IFERROR(IF(OR('Price Inputs'!Z$6="",'Price Inputs'!$I$6=""),"",'Price Inputs'!Z$6/'Price Inputs'!$I$6),"") | AA21: =IFERROR(IF(OR('Price Inputs'!AA$6="",'Price Inputs'!$I$6=""),"",'Price Inputs'!AA$6/'Price Inputs'!$I$6),"") | AB21: =IFERROR(IF(OR('Price Inputs'!AB$6="",'Price Inputs'!$I$6=""),"",'Price Inputs'!AB$6/'Price Inputs'!$I$6),"")
A22: Non-raw cost index | B22: =IF(B19="","",1) -> 1 | C22: =IF(C19="","",1) -> 1 | D22: =IF(D19="","",1) -> 1 | E22: =IF(E19="","",1) -> 1 | F22: =IF(F19="","",1) -> 1 | G22: =IF(G19="","",1) -> 1 | H22: =IF(H19="","",1) -> 1 | I22: =IF(I19="","",1) -> 1 | ... R22: =IF(R19="","",1) | S22: =IF(Assumptions!S15="","",1*(1+Assumptions!S15)) | T22: =IF(Assumptions!T15="","",S22*(1+Assumptions!T15)) | U22: =IF(Assumptions!U15="","",T22*(1+Assumptions!U15)) | V22: =IF(V19="","",1) | W22: =IF(Assumptions!W15="","",V22*(1+Assumptions!W15)) | X22: =IF(Assumptions!X15="","",W22*(1+Assumptions!X15)) | Y22: =IF(Assumptions!Y15="","",X22*(1+Assumptions!Y15)) | Z22: =IF(Assumptions!Z15="","",Y22*(1+Assumptions!Z15)) | AA22: =IF(Assumptions!AA15="","",Z22*(1+Assumptions!AA15)) | AB22: =IF(Assumptions!AB15="","",AA22*(1+Assumptions!AB15))
A23: Forecast unit cost (RMB/t) | B23: =IF(B19="","",B19) -> 11237.245 | C23: =IF(C19="","",C19) -> 9027.5761 | D23: =IF(D19="","",D19) -> 11726.247 | E23: =IF(E19="","",E19) -> 13055.507 | F23: =IF(F19="","",F19) -> 14764.774 | G23: =IF(G19="","",G19) -> 14171.852 | H23: =IF(H19="","",H19) -> 12790.768 | I23: =IF(I19="","",I19) -> 13225.646 | ... R23: =IF(R19="","",R19) | S23: =IF(OR($I$19="",S20="",S21="",S22=""),"",$I$19*(S20*S21+(1-S20)*S22)) | T23: =IF(OR($I$19="",T20="",T21="",T22=""),"",$I$19*(T20*T21+(1-T20)*T22)) | U23: =IF(OR($I$19="",U20="",U21="",U22=""),"",$I$19*(U20*U21+(1-U20)*U22)) | V23: =IF(V19="","",V19) | W23: =IF(OR($I$19="",W20="",W21="",W22=""),"",$I$19*(W20*W21+(1-W20)*W22)) | X23: =IF(OR($I$19="",X20="",X21="",X22=""),"",$I$19*(X20*X21+(1-X20)*X22)) | Y23: =IF(OR($I$19="",Y20="",Y21="",Y22=""),"",$I$19*(Y20*Y21+(1-Y20)*Y22)) | Z23: =IF(OR($I$19="",Z20="",Z21="",Z22=""),"",$I$19*(Z20*Z21+(1-Z20)*Z22)) | AA23: =IF(OR($I$19="",AA20="",AA21="",AA22=""),"",$I$19*(AA20*AA21+(1-AA20)*AA22)) | AB23: =IF(OR($I$19="",AB20="",AB21="",AB22=""),"",$I$19*(AB20*AB21+(1-AB20)*AB22))
A24: Modelled product-series cost | B24: =IF(B18="","",B18) -> 17021.133 | C24: =IF(C18="","",C18) -> 17859.814 | D24: =IF(D18="","",D18) -> 22102.639 | E24: =IF(E18="","",E18) -> 50916.478 | F24: =IF(F18="","",F18) -> 67032.076 | G24: =IF(G18="","",G18) -> 66891.14 | H24: =IF(H18="","",H18) -> 69965.5 | I24: =IF(I18="","",I18) -> 83718.342 | ... R24: =IF(R18="","",R18) | S24: =IF(OR(S17="",S23=""),"",S17*S23/100) | T24: =IF(OR(T17="",T23=""),"",T17*T23/100) | U24: =IF(OR(U17="",U23=""),"",U17*U23/100) | V24: =IF(V18="","",V18) | W24: =IF(OR(W17="",W23=""),"",W17*W23/100) | X24: =IF(OR(X17="",X23=""),"",X17*X23/100) | Y24: =IF(OR(Y17="",Y23=""),"",Y17*Y23/100) | Z24: =IF(OR(Z17="",Z23=""),"",Z17*Z23/100) | AA24: =IF(OR(AA17="",AA23=""),"",AA17*AA23/100) | AB24: =IF(OR(AB17="",AB23=""),"",AB17*AB23/100)
A27: 精细化学品及新材料系列
A28: Disclosed sales volume (10kt) | B28: ='Volume-Price'!B26 -> 32.1668 | C28: ='Volume-Price'!C26 -> 41.467 | D28: ='Volume-Price'!D26 -> 55.4944 | E28: ='Volume-Price'!E26 -> 76 | F28: ='Volume-Price'!F26 -> 95 | G28: ='Volume-Price'!G26 -> 159 | H28: ='Volume-Price'!H26 -> 203 | I28: ='Volume-Price'!I26 -> 256 | ... AB28: ='Volume-Price'!AB26
A29: Reported product-series cost | B29: 3916.3368 | C29: 5271.263 | D29: 5927.5763 | E29: 12177.199 | F29: 20124.158 | G29: 18731.475 | H29: 24661.116 | I29: 29695.758
A30: Unit cost proxy (RMB/t) | B30: =IFERROR(IF(OR(B28="",B28=0,B29=""),"",B29/B28*100),"") -> 12175.09 | C30: =IFERROR(IF(OR(C28="",C28=0,C29=""),"",C29/C28*100),"") -> 12711.947 | D30: =IFERROR(IF(OR(D28="",D28=0,D29=""),"",D29/D28*100),"") -> 10681.395 | E30: =IFERROR(IF(OR(E28="",E28=0,E29=""),"",E29/E28*100),"") -> 16022.63 | F30: =IFERROR(IF(OR(F28="",F28=0,F29=""),"",F29/F28*100),"") -> 21183.325 | G30: =IFERROR(IF(OR(G28="",G28=0,G29=""),"",G29/G28*100),"") -> 11780.802 | H30: =IFERROR(IF(OR(H28="",H28=0,H29=""),"",H29/H28*100),"") -> 12148.333 | I30: =IFERROR(IF(OR(I28="",I28=0,I29=""),"",I29/I28*100),"") -> 11599.905 | ... AB30: =IFERROR(IF(OR(AB28="",AB28=0,AB29=""),"",AB29/AB28*100),"")
A31: Raw-material share of product-series cost | B31: 0.7669 | C31: 0.7282 | D31: 0.7171 | E31: 0.7835 | F31: 0.7578 | G31: 0.6871 | H31: 0.7111 | I31: 0.6969 | S31: =IF(Assumptions!S20="","",Assumptions!S20) | T31: =IF(Assumptions!T20="","",Assumptions!T20) | U31: =IF(Assumptions!U20="","",Assumptions!U20) | V31: =IF(Assumptions!V20="","",Assumptions!V20) | W31: =IF(Assumptions!W20="","",Assumptions!W20) | X31: =IF(Assumptions!X20="","",Assumptions!X20) | Y31: =IF(Assumptions!Y20="","",Assumptions!Y20) | Z31: =IF(Assumptions!Z20="","",Assumptions!Z20) | ... AB31: =IF(Assumptions!AB20="","",Assumptions!AB20)
A32: Raw price index (2025A benzene = 1.00x) | B32: =IFERROR(IF(OR('Price Inputs'!B$6="",'Price Inputs'!$I$6=""),"",'Price Inputs'!B$6/'Price Inputs'!$I$6),"") | C32: =IFERROR(IF(OR('Price Inputs'!C$6="",'Price Inputs'!$I$6=""),"",'Price Inputs'!C$6/'Price Inputs'!$I$6),"") -> 0.8035913 | D32: =IFERROR(IF(OR('Price Inputs'!D$6="",'Price Inputs'!$I$6=""),"",'Price Inputs'!D$6/'Price Inputs'!$I$6),"") -> 0.62823793 | E32: =IFERROR(IF(OR('Price Inputs'!E$6="",'Price Inputs'!$I$6=""),"",'Price Inputs'!E$6/'Price Inputs'!$I$6),"") -> 1.1367125 | F32: =IFERROR(IF(OR('Price Inputs'!F$6="",'Price Inputs'!$I$6=""),"",'Price Inputs'!F$6/'Price Inputs'!$I$6),"") -> 1.2991685 | G32: =IFERROR(IF(OR('Price Inputs'!G$6="",'Price Inputs'!$I$6=""),"",'Price Inputs'!G$6/'Price Inputs'!$I$6),"") -> 1.1592581 | H32: =IFERROR(IF(OR('Price Inputs'!H$6="",'Price Inputs'!$I$6=""),"",'Price Inputs'!H$6/'Price Inputs'!$I$6),"") -> 1.3271506 | I32: =IFERROR(IF(OR('Price Inputs'!I$6="",'Price Inputs'!$I$6=""),"",'Price Inputs'!I$6/'Price Inputs'!$I$6),"") -> 1 | ... U32: =IFERROR(IF(OR('Price Inputs'!U$6="",'Price Inputs'!$I$6=""),"",'Price Inputs'!U$6/'Price Inputs'!$I$6),"") | V32: ='Price Inputs'!V7 | W32: =IFERROR(IF(OR('Price Inputs'!W$6="",'Price Inputs'!$I$6=""),"",'Price Inputs'!W$6/'Price Inputs'!$I$6),"") | X32: =IFERROR(IF(OR('Price Inputs'!X$6="",'Price Inputs'!$I$6=""),"",'Price Inputs'!X$6/'Price Inputs'!$I$6),"") | Y32: =IFERROR(IF(OR('Price Inputs'!Y$6="",'Price Inputs'!$I$6=""),"",'Price Inputs'!Y$6/'Price Inputs'!$I$6),"") | Z32: =IFERROR(IF(OR('Price Inputs'!Z$6="",'Price Inputs'!$I$6=""),"",'Price Inputs'!Z$6/'Price Inputs'!$I$6),"") | AA32: =IFERROR(IF(OR('Price Inputs'!AA$6="",'Price Inputs'!$I$6=""),"",'Price Inputs'!AA$6/'Price Inputs'!$I$6),"") | AB32: =IFERROR(IF(OR('Price Inputs'!AB$6="",'Price Inputs'!$I$6=""),"",'Price Inputs'!AB$6/'Price Inputs'!$I$6),"")
A33: Non-raw cost index | B33: =IF(B30="","",1) -> 1 | C33: =IF(C30="","",1) -> 1 | D33: =IF(D30="","",1) -> 1 | E33: =IF(E30="","",1) -> 1 | F33: =IF(F30="","",1) -> 1 | G33: =IF(G30="","",1) -> 1 | H33: =IF(H30="","",1) -> 1 | I33: =IF(I30="","",1) -> 1 | ... R33: =IF(R30="","",1) | S33: =IF(Assumptions!S21="","",1*(1+Assumptions!S21)) | T33: =IF(Assumptions!T21="","",S33*(1+Assumptions!T21)) | U33: =IF(Assumptions!U21="","",T33*(1+Assumptions!U21)) | V33: =IF(V30="","",1) | W33: =IF(Assumptions!W21="","",V33*(1+Assumptions!W21)) | X33: =IF(Assumptions!X21="","",W33*(1+Assumptions!X21)) | Y33: =IF(Assumptions!Y21="","",X33*(1+Assumptions!Y21)) | Z33: =IF(Assumptions!Z21="","",Y33*(1+Assumptions!Z21)) | AA33: =IF(Assumptions!AA21="","",Z33*(1+Assumptions!AA21)) | AB33: =IF(Assumptions!AB21="","",AA33*(1+Assumptions!AB21))
A34: Forecast unit cost (RMB/t) | B34: =IF(B30="","",B30) -> 12175.09 | C34: =IF(C30="","",C30) -> 12711.947 | D34: =IF(D30="","",D30) -> 10681.395 | E34: =IF(E30="","",E30) -> 16022.63 | F34: =IF(F30="","",F30) -> 21183.325 | G34: =IF(G30="","",G30) -> 11780.802 | H34: =IF(H30="","",H30) -> 12148.333 | I34: =IF(I30="","",I30) -> 11599.905 | ... R34: =IF(R30="","",R30) | S34: =IF(OR($I$30="",S31="",S32="",S33=""),"",$I$30*(S31*S32+(1-S31)*S33)) | T34: =IF(OR($I$30="",T31="",T32="",T33=""),"",$I$30*(T31*T32+(1-T31)*T33)) | U34: =IF(OR($I$30="",U31="",U32="",U33=""),"",$I$30*(U31*U32+(1-U31)*U33)) | V34: =IF(V30="","",V30) | W34: =IF(OR($I$30="",W31="",W32="",W33=""),"",$I$30*(W31*W32+(1-W31)*W33)) | X34: =IF(OR($I$30="",X31="",X32="",X33=""),"",$I$30*(X31*X32+(1-X31)*X33)) | Y34: =IF(OR($I$30="",Y31="",Y32="",Y33=""),"",$I$30*(Y31*Y32+(1-Y31)*Y33)) | Z34: =IF(OR($I$30="",Z31="",Z32="",Z33=""),"",$I$30*(Z31*Z32+(1-Z31)*Z33)) | AA34: =IF(OR($I$30="",AA31="",AA32="",AA33=""),"",$I$30*(AA31*AA32+(1-AA31)*AA33)) | AB34: =IF(OR($I$30="",AB31="",AB32="",AB33=""),"",$I$30*(AB31*AB32+(1-AB31)*AB33))
A35: Modelled product-series cost | B35: =IF(B29="","",B29) -> 3916.3368 | C35: =IF(C29="","",C29) -> 5271.263 | D35: =IF(D29="","",D29) -> 5927.5763 | E35: =IF(E29="","",E29) -> 12177.199 | F35: =IF(F29="","",F29) -> 20124.158 | G35: =IF(G29="","",G29) -> 18731.475 | H35: =IF(H29="","",H29) -> 24661.116 | I35: =IF(I29="","",I29) -> 29695.758 | ... R35: =IF(R29="","",R29) | S35: =IF(OR(S28="",S34=""),"",S28*S34/100) | T35: =IF(OR(T28="",T34=""),"",T28*T34/100) | U35: =IF(OR(U28="",U34=""),"",U28*U34/100) | V35: =IF(V29="","",V29) | W35: =IF(OR(W28="",W34=""),"",W28*W34/100) | X35: =IF(OR(X28="",X34=""),"",X28*X34/100) | Y35: =IF(OR(Y28="",Y34=""),"",Y28*Y34/100) | Z35: =IF(OR(Z28="",Z34=""),"",Z28*Z34/100) | AA35: =IF(OR(AA28="",AA34=""),"",AA28*AA34/100) | AB35: =IF(OR(AB28="",AB34=""),"",AB28*AB34/100)

Sheet Segment P&L
A1: Segment P&L
A2: Historical residuals reconcile disclosed product tables to consolidated statements; forecast residuals are formula-driven.
A4: RMB mm unless stated | B4: 2018A | C4: 2019A | D4: 2020A | E4: 2021A | F4: 2022A | G4: 2023A | H4: 2024A | I4: 2025A | J4: 2024Q1A | K4: 2024Q2A | L4: 2024Q3A | M4: 2024Q4A | N4: 2025Q1A | O4: 2025Q2A | P4: 2025Q3A | Q4: 2025Q4A | R4: 2026Q1A | S4: 2026E | T4: 2027E | U4: 2028E | V4: 2026Q2A | W4: 2026Q3E | X4: 2026Q4E | Y4: 2027Q1E | Z4: 2027Q2E | AA4: 2027Q3E | AB4: 2027Q4E
A5: 聚氨酯系列
A6: Revenue | B6: ='Volume-Price'!B12 -> 30951.892 | C6: ='Volume-Price'!C12 -> 31858.132 | D6: ='Volume-Price'!D12 -> 34416.866 | E6: ='Volume-Price'!E12 -> 60492.225 | F6: ='Volume-Price'!F12 -> 62895.628 | G6: ='Volume-Price'!G12 -> 67386.16 | H6: ='Volume-Price'!H12 -> 75844.15 | I6: ='Volume-Price'!I12 -> 75058.224 | ... AB6: ='Volume-Price'!AB12
A7: Cost | B7: ='Cost Bridge'!B13 -> 15384.314 | C7: ='Cost Bridge'!C13 -> 18687.947 | D7: ='Cost Bridge'!D13 -> 19441.716 | E7: ='Cost Bridge'!E13 -> 39277.435 | F7: ='Cost Bridge'!F13 -> 47518.326 | G7: ='Cost Bridge'!G13 -> 48725.3 | H7: ='Cost Bridge'!H13 -> 56009.192 | I7: ='Cost Bridge'!I13 -> 54880.846 | ... AB7: ='Cost Bridge'!AB13
A8: Gross profit | B8: =IF(OR(B6="",B7=""),"",B6-B7) -> 15567.578 | C8: =IF(OR(C6="",C7=""),"",C6-C7) -> 13170.185 | D8: =IF(OR(D6="",D7=""),"",D6-D7) -> 14975.15 | E8: =IF(OR(E6="",E7=""),"",E6-E7) -> 21214.79 | F8: =IF(OR(F6="",F7=""),"",F6-F7) -> 15377.302 | G8: =IF(OR(G6="",G7=""),"",G6-G7) -> 18660.86 | H8: =IF(OR(H6="",H7=""),"",H6-H7) -> 19834.958 | I8: =IF(OR(I6="",I7=""),"",I6-I7) -> 20177.378 | ... AB8: =IF(OR(AB6="",AB7=""),"",AB6-AB7)
A9: Gross margin | B9: =IFERROR(IF(OR(B6="",B6=0,B8=""),"",B8/B6),"") -> 0.50296046 | C9: =IFERROR(IF(OR(C6="",C6=0,C8=""),"",C8/C6),"") -> 0.41340104 | D9: =IFERROR(IF(OR(D6="",D6=0,D8=""),"",D8/D6),"") -> 0.4351108 | E9: =IFERROR(IF(OR(E6="",E6=0,E8=""),"",E8/E6),"") -> 0.35070275 | F9: =IFERROR(IF(OR(F6="",F6=0,F8=""),"",F8/F6),"") -> 0.24448921 | G9: =IFERROR(IF(OR(G6="",G6=0,G8=""),"",G8/G6),"") -> 0.27692422 | H9: =IFERROR(IF(OR(H6="",H6=0,H8=""),"",H8/H6),"") -> 0.26152259 | I9: =IFERROR(IF(OR(I6="",I6=0,I8=""),"",I8/I6),"") -> 0.26882302 | ... AB9: =IFERROR(IF(OR(AB6="",AB6=0,AB8=""),"",AB8/AB6),"")
A11: 石化系列
A12: Revenue | B12: ='Volume-Price'!B22 -> 18907.546 | C12: ='Volume-Price'!C22 -> 20102.036 | D12: ='Volume-Price'!D22 -> 23084.987 | E12: ='Volume-Price'!E22 -> 61409.365 | F12: ='Volume-Price'!F22 -> 69635.164 | G12: ='Volume-Price'!G22 -> 69327.924 | H12: ='Volume-Price'!H22 -> 72518.272 | I12: ='Volume-Price'!I22 -> 84203.81 | ... AB12: ='Volume-Price'!AB22
A13: Cost | B13: ='Cost Bridge'!B24 -> 17021.133 | C13: ='Cost Bridge'!C24 -> 17859.814 | D13: ='Cost Bridge'!D24 -> 22102.639 | E13: ='Cost Bridge'!E24 -> 50916.478 | F13: ='Cost Bridge'!F24 -> 67032.076 | G13: ='Cost Bridge'!G24 -> 66891.14 | H13: ='Cost Bridge'!H24 -> 69965.5 | I13: ='Cost Bridge'!I24 -> 83718.342 | ... AB13: ='Cost Bridge'!AB24
A14: Gross profit | B14: =IF(OR(B12="",B13=""),"",B12-B13) -> 1886.4125 | C14: =IF(OR(C12="",C13=""),"",C12-C13) -> 2242.2222 | D14: =IF(OR(D12="",D13=""),"",D12-D13) -> 982.34823 | E14: =IF(OR(E12="",E13=""),"",E12-E13) -> 10492.887 | F14: =IF(OR(F12="",F13=""),"",F12-F13) -> 2603.0878 | G14: =IF(OR(G12="",G13=""),"",G12-G13) -> 2436.7839 | H14: =IF(OR(H12="",H13=""),"",H12-H13) -> 2552.7716 | I14: =IF(OR(I12="",I13=""),"",I12-I13) -> 485.46897 | ... AB14: =IF(OR(AB12="",AB13=""),"",AB12-AB13)
A15: Gross margin | B15: =IFERROR(IF(OR(B12="",B12=0,B14=""),"",B14/B12),"") -> 0.099770352 | C15: =IFERROR(IF(OR(C12="",C12=0,C14=""),"",C14/C12),"") -> 0.11154204 | D15: =IFERROR(IF(OR(D12="",D12=0,D14=""),"",D14/D12),"") -> 0.042553554 | E15: =IFERROR(IF(OR(E12="",E12=0,E14=""),"",E14/E12),"") -> 0.17086786 | F15: =IFERROR(IF(OR(F12="",F12=0,F14=""),"",F14/F12),"") -> 0.037381801 | G15: =IFERROR(IF(OR(G12="",G12=0,G14=""),"",G14/G12),"") -> 0.035148664 | H15: =IFERROR(IF(OR(H12="",H12=0,H14=""),"",H14/H12),"") -> 0.035201771 | I15: =IFERROR(IF(OR(I12="",I12=0,I14=""),"",I14/I12),"") -> 0.0057654038 | ... AB15: =IFERROR(IF(OR(AB12="",AB12=0,AB14=""),"",AB14/AB12),"")
A17: 精细化学品及新材料系列
A18: Revenue | B18: ='Volume-Price'!B32 -> 5702.9624 | C18: ='Volume-Price'!C32 -> 7087.781 | D18: ='Volume-Price'!D32 -> 7947.8577 | E18: ='Volume-Price'!E32 -> 15463.788 | F18: ='Volume-Price'!F32 -> 20124.158 | G18: ='Volume-Price'!G32 -> 23836.062 | H18: ='Volume-Price'!H32 -> 28273.081 | I18: ='Volume-Price'!I32 -> 33189.13 | ... AB18: ='Volume-Price'!AB32
A19: Cost | B19: ='Cost Bridge'!B35 -> 3916.3368 | C19: ='Cost Bridge'!C35 -> 5271.263 | D19: ='Cost Bridge'!D35 -> 5927.5763 | E19: ='Cost Bridge'!E35 -> 12177.199 | F19: ='Cost Bridge'!F35 -> 20124.158 | G19: ='Cost Bridge'!G35 -> 18731.475 | H19: ='Cost Bridge'!H35 -> 24661.116 | I19: ='Cost Bridge'!I35 -> 29695.758 | ... AB19: ='Cost Bridge'!AB35
A20: Gross profit | B20: =IF(OR(B18="",B19=""),"",B18-B19) -> 1786.6255 | C20: =IF(OR(C18="",C19=""),"",C18-C19) -> 1816.518 | D20: =IF(OR(D18="",D19=""),"",D18-D19) -> 2020.2813 | E20: =IF(OR(E18="",E19=""),"",E18-E19) -> 3286.5893 | F20: =IF(OR(F18="",F19=""),"",F18-F19) -> 0 | G20: =IF(OR(G18="",G19=""),"",G18-G19) -> 5104.5873 | H20: =IF(OR(H18="",H19=""),"",H18-H19) -> 3611.9642 | I20: =IF(OR(I18="",I19=""),"",I18-I19) -> 3493.3719 | ... AB20: =IF(OR(AB18="",AB19=""),"",AB18-AB19)
A21: Gross margin | B21: =IFERROR(IF(OR(B18="",B18=0,B20=""),"",B20/B18),"") -> 0.31328026 | C21: =IFERROR(IF(OR(C18="",C18=0,C20=""),"",C20/C18),"") -> 0.25628867 | D21: =IFERROR(IF(OR(D18="",D18=0,D20=""),"",D20/D18),"") -> 0.25419194 | E21: =IFERROR(IF(OR(E18="",E18=0,E20=""),"",E20/E18),"") -> 0.21253455 | F21: =IFERROR(IF(OR(F18="",F18=0,F20=""),"",F20/F18),"") -> 0 | G21: =IFERROR(IF(OR(G18="",G18=0,G20=""),"",G20/G18),"") -> 0.21415396 | H21: =IFERROR(IF(OR(H18="",H18=0,H20=""),"",H20/H18),"") -> 0.12775276 | I21: =IFERROR(IF(OR(I18="",I18=0,I20=""),"",I20/I18),"") -> 0.10525651 | ... AB21: =IFERROR(IF(OR(AB18="",AB18=0,AB20=""),"",AB20/AB18),"")
A23: Other, eliminations and reconciliation
A24: Other / residual revenue — disclosed or modelled | B24: 4299.5053 | C24: 8241.5331 | D24: 6829.8447 | E24: 18437.09 | F24: 25478.329 | G24: 27471.413 | H24: 21134.172 | I24: 26217.909 | S24: =IF(Assumptions!S28="","",I30*(1+Assumptions!S28)) | T24: =IF(Assumptions!T28="","",S30*(1+Assumptions!T28)) | U24: =IF(Assumptions!U28="","",T30*(1+Assumptions!U28)) | W24: =IF(Assumptions!W28="","",V30*(1+Assumptions!W28)) | X24: =IF(Assumptions!X28="","",W30*(1+Assumptions!X28)) | Y24: =IF(Assumptions!Y28="","",X30*(1+Assumptions!Y28)) | Z24: =IF(Assumptions!Z28="","",Y30*(1+Assumptions!Z28)) | AA24: =IF(Assumptions!AA28="","",Z30*(1+Assumptions!AA28)) | AB24: =IF(Assumptions!AB28="","",AA30*(1+Assumptions!AB28))
A25: Other / residual cost — disclosed or modelled | B25: 3074.6892 | C25: 6465.2243 | D25: 5185.1021 | E25: 15185.843 | F25: 21688.846 | G25: 24807.834 | H25: 17801.322 | I25: 22937.677 | S25: =IF(Assumptions!S28="","",I25*(1+Assumptions!S28)) | T25: =IF(Assumptions!T28="","",S25*(1+Assumptions!T28)) | U25: =IF(Assumptions!U28="","",T25*(1+Assumptions!U28)) | W25: =IF(Assumptions!W28="","",V25*(1+Assumptions!W28)) | X25: =IF(Assumptions!X28="","",W25*(1+Assumptions!X28)) | Y25: =IF(Assumptions!Y28="","",X25*(1+Assumptions!Y28)) | Z25: =IF(Assumptions!Z28="","",Y25*(1+Assumptions!Z28)) | AA25: =IF(Assumptions!AA28="","",Z25*(1+Assumptions!AA28)) | AB25: =IF(Assumptions!AB28="","",AA25*(1+Assumptions!AB28))
A26: Eliminations revenue — disclosed | E26: -10901.876 | F26: -13625.269 | G26: -14454.748 | H26: -16419.81 | I26: -16286.562
A27: Eliminations cost — disclosed | E27: -10820.555 | F27: -13411.89 | G27: -14530.872 | H27: -16381.419 | I27: -16307.2
A28: Product-table subtotal — revenue | B28: =IF(COUNT(B6,B12,B18)=0,"",SUM(B6,B12,B18,B24,B26)) -> 59861.905 | C28: =IF(COUNT(C6,C12,C18)=0,"",SUM(C6,C12,C18,C24,C26)) -> 67289.482 | D28: =IF(COUNT(D6,D12,D18)=0,"",SUM(D6,D12,D18,D24,D26)) -> 72279.555 | E28: =IF(COUNT(E6,E12,E18)=0,"",SUM(E6,E12,E18,E24,E26)) -> 144900.59 | F28: =IF(COUNT(F6,F12,F18)=0,"",SUM(F6,F12,F18,F24,F26)) -> 164508.01 | G28: =IF(COUNT(G6,G12,G18)=0,"",SUM(G6,G12,G18,G24,G26)) -> 173566.81 | H28: =IF(COUNT(H6,H12,H18)=0,"",SUM(H6,H12,H18,H24,H26)) -> 181349.86 | I28: =IF(COUNT(I6,I12,I18)=0,"",SUM(I6,I12,I18,I24,I26)) -> 202382.51 | ... AB28: =IF(COUNT(AB6,AB12,AB18)=0,"",SUM(AB6,AB12,AB18,AB24,AB26))
A29: Product-table subtotal — cost | B29: =IF(COUNT(B7,B13,B19)=0,"",SUM(B7,B13,B19,B25,B27)) -> 39396.473 | C29: =IF(COUNT(C7,C13,C19)=0,"",SUM(C7,C13,C19,C25,C27)) -> 48284.248 | D29: =IF(COUNT(D7,D13,D19)=0,"",SUM(D7,D13,D19,D25,D27)) -> 52657.033 | E29: =IF(COUNT(E7,E13,E19)=0,"",SUM(E7,E13,E19,E25,E27)) -> 106736.4 | F29: =IF(COUNT(F7,F13,F19)=0,"",SUM(F7,F13,F19,F25,F27)) -> 142951.52 | G29: =IF(COUNT(G7,G13,G19)=0,"",SUM(G7,G13,G19,G25,G27)) -> 144624.88 | H29: =IF(COUNT(H7,H13,H19)=0,"",SUM(H7,H13,H19,H25,H27)) -> 152055.71 | I29: =IF(COUNT(I7,I13,I19)=0,"",SUM(I7,I13,I19,I25,I27)) -> 174925.42 | ... AB29: =IF(COUNT(AB7,AB13,AB19)=0,"",SUM(AB7,AB13,AB19,AB25,AB27))
A30: Boundary residual — revenue | B30: =IF('Consol P&L'!B$6="","",'Consol P&L'!B$6-IF(B28="",0,B28)) -> 759.28805 | C30: =IF('Consol P&L'!C$6="","",'Consol P&L'!C$6-IF(C28="",0,C28)) -> 761.18669 | D30: =IF('Consol P&L'!D$6="","",'Consol P&L'!D$6-IF(D28="",0,D28)) -> 1153.4132 | E30: =IF('Consol P&L'!E$6="","",'Consol P&L'!E$6-IF(E28="",0,E28)) -> 637.22517 | F30: =IF('Consol P&L'!F$6="","",'Consol P&L'!F$6-IF(F28="",0,F28)) -> 1057.4749 | G30: =IF('Consol P&L'!G$6="","",'Consol P&L'!G$6-IF(G28="",0,G28)) -> 1794.1233 | H30: =IF('Consol P&L'!H$6="","",'Consol P&L'!H$6-IF(H28="",0,H28)) -> 719.25465 | I30: =IF('Consol P&L'!I$6="","",'Consol P&L'!I$6-IF(I28="",0,I28)) -> 852.06181 | ... R30: =IF('Consol P&L'!R$6="","",'Consol P&L'!R$6-IF(R28="",0,R28)) -> 3907.2154 | S30: ="" | T30: ="" | U30: ="" | V30: =IF('Consol P&L'!V$6="","",'Consol P&L'!V$6-IF(V28="",0,V28)) -> 166.79059 | W30: ="" | X30: ="" | Y30: ="" | Z30: ="" | AA30: ="" | AB30: =""
A31: Boundary residual — cost | B31: =IF('Consol P&L'!B$9="","",'Consol P&L'!B$9-IF(B29="",0,B29)) -> 717.88358 | C31: =IF('Consol P&L'!C$9="","",'Consol P&L'!C$9-IF(C29="",0,C29)) -> 713.36235 | D31: =IF('Consol P&L'!D$9="","",'Consol P&L'!D$9-IF(D29="",0,D29)) -> 1108.872 | E31: =IF('Consol P&L'!E$9="","",'Consol P&L'!E$9-IF(E29="",0,E29)) -> 580.10832 | F31: =IF('Consol P&L'!F$9="","",'Consol P&L'!F$9-IF(F29="",0,F29)) -> -4819.2927 | G31: =IF('Consol P&L'!G$9="","",'Consol P&L'!G$9-IF(G29="",0,G29)) -> 1301.4813 | H31: =IF('Consol P&L'!H$9="","",'Consol P&L'!H$9-IF(H29="",0,H29)) -> 586.87192 | I31: =IF('Consol P&L'!I$9="","",'Consol P&L'!I$9-IF(I29="",0,I29)) -> 644.16257 | ... R31: =IF('Consol P&L'!R$9="","",'Consol P&L'!R$9-IF(R29="",0,R29)) -> 46091.339 | S31: ="" | T31: ="" | U31: ="" | V31: =IF('Consol P&L'!V$9="","",'Consol P&L'!V$9-IF(V29="",0,V29)) -> 52840.375 | W31: ="" | X31: ="" | Y31: ="" | Z31: ="" | AA31: ="" | AB31: =""
A32: Consolidated schedule revenue | B32: =IF('Consol P&L'!B$6="","",SUM(B28,B30)) -> 60621.193 | C32: =IF('Consol P&L'!C$6="","",SUM(C28,C30)) -> 68050.669 | D32: =IF('Consol P&L'!D$6="","",SUM(D28,D30)) -> 73432.968 | E32: =IF('Consol P&L'!E$6="","",SUM(E28,E30)) -> 145537.82 | F32: =IF('Consol P&L'!F$6="","",SUM(F28,F30)) -> 165565.48 | G32: =IF('Consol P&L'!G$6="","",SUM(G28,G30)) -> 175360.94 | H32: =IF('Consol P&L'!H$6="","",SUM(H28,H30)) -> 182069.12 | I32: =IF('Consol P&L'!I$6="","",SUM(I28,I30)) -> 203234.57 | ... R32: =IF('Consol P&L'!R$6="","",SUM(R28,R30)) -> 54052.165 | S32: =IF(S28="","",S28) | T32: =IF(T28="","",T28) | U32: =IF(U28="","",U28) | V32: =IF('Consol P&L'!V$6="","",SUM(V28,V30)) -> 65263.698 | W32: =IF(W28="","",W28) | X32: =IF(X28="","",X28) | Y32: =IF(Y28="","",Y28) | Z32: =IF(Z28="","",Z28) | AA32: =IF(AA28="","",AA28) | AB32: =IF(AB28="","",AB28)
A33: Consolidated schedule cost | B33: =IF('Consol P&L'!B$9="","",SUM(B29,B31)) -> 40114.357 | C33: =IF('Consol P&L'!C$9="","",SUM(C29,C31)) -> 48997.611 | D33: =IF('Consol P&L'!D$9="","",SUM(D29,D31)) -> 53765.905 | E33: =IF('Consol P&L'!E$9="","",SUM(E29,E31)) -> 107316.51 | F33: =IF('Consol P&L'!F$9="","",SUM(F29,F31)) -> 138132.22 | G33: =IF('Consol P&L'!G$9="","",SUM(G29,G31)) -> 145926.36 | H33: =IF('Consol P&L'!H$9="","",SUM(H29,H31)) -> 152642.58 | I33: =IF('Consol P&L'!I$9="","",SUM(I29,I31)) -> 175569.58 | ... R33: =IF('Consol P&L'!R$9="","",SUM(R29,R31)) -> 46091.339 | S33: =IF(S29="","",S29) | T33: =IF(T29="","",T29) | U33: =IF(U29="","",U29) | V33: =IF('Consol P&L'!V$9="","",SUM(V29,V31)) -> 52840.375 | W33: =IF(W29="","",W29) | X33: =IF(X29="","",X29) | Y33: =IF(Y29="","",Y29) | Z33: =IF(Z29="","",Z29) | AA33: =IF(AA29="","",AA29) | AB33: =IF(AB29="","",AB29)
A34: Consolidated schedule gross profit | B34: =IF(OR(B32="",B33=""),"",B32-B33) -> 20506.837 | C34: =IF(OR(C32="",C33=""),"",C32-C33) -> 19053.058 | D34: =IF(OR(D32="",D33=""),"",D32-D33) -> 19667.063 | E34: =IF(OR(E32="",E33=""),"",E32-E33) -> 38221.309 | F34: =IF(OR(F32="",F33=""),"",F32-F33) -> 27433.262 | G34: =IF(OR(G32="",G33=""),"",G32-G33) -> 29434.576 | H34: =IF(OR(H32="",H33=""),"",H32-H33) -> 29426.536 | I34: =IF(OR(I32="",I33=""),"",I32-I33) -> 27664.989 | ... AB34: =IF(OR(AB32="",AB33=""),"",AB32-AB33)
A35: Consolidated schedule gross margin | B35: =IFERROR(IF(OR(B32="",B32=0,B34=""),"",B34/B32),"") -> 0.33827834 | C35: =IFERROR(IF(OR(C32="",C32=0,C34=""),"",C34/C32),"") -> 0.27998341 | D35: =IFERROR(IF(OR(D32="",D32=0,D34=""),"",D34/D32),"") -> 0.26782335 | E35: =IFERROR(IF(OR(E32="",E32=0,E34=""),"",E34/E32),"") -> 0.26262115 | F35: =IFERROR(IF(OR(F32="",F32=0,F34=""),"",F34/F32),"") -> 0.16569433 | G35: =IFERROR(IF(OR(G32="",G32=0,G34=""),"",G34/G32),"") -> 0.16785139 | H35: =IFERROR(IF(OR(H32="",H32=0,H34=""),"",H34/H32),"") -> 0.16162288 | I35: =IFERROR(IF(OR(I32="",I32=0,I34=""),"",I34/I32),"") -> 0.13612344 | ... AB35: =IFERROR(IF(OR(AB32="",AB32=0,AB34=""),"",AB34/AB32),"")

Sheet Consol P&L
A1: Consolidated P&L
A2: Annual filing actuals and standalone quarterly filing actuals / arithmetic differences.
A4: RMB mm unless stated | B4: 2018A | C4: 2019A | D4: 2020A | E4: 2021A | F4: 2022A | G4: 2023A | H4: 2024A | I4: 2025A | J4: 2024Q1A | K4: 2024Q2A | L4: 2024Q3A | M4: 2024Q4A | N4: 2025Q1A | O4: 2025Q2A | P4: 2025Q3A | Q4: 2025Q4A | R4: 2026Q1A | S4: 2026E | T4: 2027E | U4: 2028E | V4: 2026Q2A | W4: 2026Q3E | X4: 2026Q4E | Y4: 2027Q1E | Z4: 2027Q2E | AA4: 2027Q3E | AB4: 2027Q4E
A5: Segment schedule revenue | B5: ='Segment P&L'!B32 -> 60621.193 | C5: ='Segment P&L'!C32 -> 68050.669 | D5: ='Segment P&L'!D32 -> 73432.968 | E5: ='Segment P&L'!E32 -> 145537.82 | F5: ='Segment P&L'!F32 -> 165565.48 | G5: ='Segment P&L'!G32 -> 175360.94 | H5: ='Segment P&L'!H32 -> 182069.12 | I5: ='Segment P&L'!I32 -> 203234.57 | ... AB5: ='Segment P&L'!AB32
A6: Consolidated revenue — filing actual / forecast | B6: 60621.193 | C6: 68050.669 | D6: 73432.968 | E6: 145537.82 | F6: 165565.48 | G6: 175360.94 | H6: 182069.12 | I6: 203234.57 | J6: 46161.005 | K6: 50906.359 | L6: 50536.787 | M6: 34464.969 | N6: 43067.851 | O6: 47833.586 | P6: 53324.359 | Q6: 59008.778 | R6: 54052.165 | S6: =IF(S5="","",S5) | T6: =IF(T5="","",T5) | U6: =IF(U5="","",U5) | V6: 65263.698 | W6: =IF(W5="","",W5) | X6: =IF(X5="","",X5) | Y6: =IF(Y5="","",Y5) | Z6: =IF(Z5="","",Z5) | AA6: =IF(AA5="","",AA5) | AB6: =IF(AB5="","",AB5)
A7: Revenue bridge difference | B7: =IF(OR(B5="",B6=""),"",B5-B6) -> 0 | C7: =IF(OR(C5="",C6=""),"",C5-C6) -> 0 | D7: =IF(OR(D5="",D6=""),"",D5-D6) -> 0 | E7: =IF(OR(E5="",E6=""),"",E5-E6) -> 0 | F7: =IF(OR(F5="",F6=""),"",F5-F6) -> 0 | G7: =IF(OR(G5="",G6=""),"",G5-G6) -> 0 | H7: =IF(OR(H5="",H6=""),"",H5-H6) -> 0 | I7: =IF(OR(I5="",I6=""),"",I5-I6) -> 0 | ... AB7: =IF(OR(AB5="",AB6=""),"",AB5-AB6)
A8: Segment schedule cost | B8: ='Segment P&L'!B33 -> 40114.357 | C8: ='Segment P&L'!C33 -> 48997.611 | D8: ='Segment P&L'!D33 -> 53765.905 | E8: ='Segment P&L'!E33 -> 107316.51 | F8: ='Segment P&L'!F33 -> 138132.22 | G8: ='Segment P&L'!G33 -> 145926.36 | H8: ='Segment P&L'!H33 -> 152642.58 | I8: ='Segment P&L'!I33 -> 175569.58 | ... AB8: ='Segment P&L'!AB33
A9: Consolidated cost of sales — filing actual / forecast | B9: 40114.357 | C9: 48997.611 | D9: 53765.905 | E9: 107316.51 | F9: 138132.22 | G9: 145926.36 | H9: 152642.58 | I9: 175569.58 | J9: 38023.68 | K9: 43111.086 | L9: 43766.424 | M9: 27741.393 | N9: 36304.079 | O9: 42015.467 | P9: 46517.255 | Q9: 50732.783 | R9: 46091.339 | S9: =IF(S8="","",S8) | T9: =IF(T8="","",T8) | U9: =IF(U8="","",U8) | V9: 52840.375 | W9: =IF(W8="","",W8) | X9: =IF(X8="","",X8) | Y9: =IF(Y8="","",Y8) | Z9: =IF(Z8="","",Z8) | AA9: =IF(AA8="","",AA8) | AB9: =IF(AB8="","",AB8)
A10: Cost bridge difference | B10: =IF(OR(B8="",B9=""),"",B8-B9) -> 0 | C10: =IF(OR(C8="",C9=""),"",C8-C9) -> 0 | D10: =IF(OR(D8="",D9=""),"",D8-D9) -> 0 | E10: =IF(OR(E8="",E9=""),"",E8-E9) -> 0 | F10: =IF(OR(F8="",F9=""),"",F8-F9) -> 0 | G10: =IF(OR(G8="",G9=""),"",G8-G9) -> 0 | H10: =IF(OR(H8="",H9=""),"",H8-H9) -> 0 | I10: =IF(OR(I8="",I9=""),"",I8-I9) -> 0 | ... AB10: =IF(OR(AB8="",AB9=""),"",AB8-AB9)
A11: Gross profit | B11: =IF(OR(B6="",B9=""),"",B6-B9) -> 20506.837 | C11: =IF(OR(C6="",C9=""),"",C6-C9) -> 19053.058 | D11: =IF(OR(D6="",D9=""),"",D6-D9) -> 19667.063 | E11: =IF(OR(E6="",E9=""),"",E6-E9) -> 38221.309 | F11: =IF(OR(F6="",F9=""),"",F6-F9) -> 27433.262 | G11: =IF(OR(G6="",G9=""),"",G6-G9) -> 29434.576 | H11: =IF(OR(H6="",H9=""),"",H6-H9) -> 29426.536 | I11: =IF(OR(I6="",I9=""),"",I6-I9) -> 27664.989 | ... AB11: =IF(OR(AB6="",AB9=""),"",AB6-AB9)
A12: Gross margin | B12: =IFERROR(IF(OR(B6="",B6=0,B11=""),"",B11/B6),"") -> 0.33827834 | C12: =IFERROR(IF(OR(C6="",C6=0,C11=""),"",C11/C6),"") -> 0.27998341 | D12: =IFERROR(IF(OR(D6="",D6=0,D11=""),"",D11/D6),"") -> 0.26782335 | E12: =IFERROR(IF(OR(E6="",E6=0,E11=""),"",E11/E6),"") -> 0.26262115 | F12: =IFERROR(IF(OR(F6="",F6=0,F11=""),"",F11/F6),"") -> 0.16569433 | G12: =IFERROR(IF(OR(G6="",G6=0,G11=""),"",G11/G6),"") -> 0.16785139 | H12: =IFERROR(IF(OR(H6="",H6=0,H11=""),"",H11/H6),"") -> 0.16162288 | I12: =IFERROR(IF(OR(I6="",I6=0,I11=""),"",I11/I6),"") -> 0.13612344 | ... AB12: =IFERROR(IF(OR(AB6="",AB6=0,AB11=""),"",AB11/AB6),"")
A13: Operating profit — filing actual / forecast | B13: 16084.982 | C13: 12296.961 | D13: 11824.928 | E13: 29425.48 | F13: 19838.567 | G13: 20389.187 | H13: 17965.675 | I13: 16666.044 | J13: 5370.1718 | K13: 5200.5654 | L13: 3985.8054 | M13: 3409.1322 | N13: 4015.8185 | O13: 3626.7573 | P13: 4139.4424 | Q13: 4884.0256 | R13: 5304.7813 | S13: =IF(OR(S11="",S15=""),"",S11-S6*S15) | T13: =IF(OR(T11="",T15=""),"",T11-T6*T15) | U13: =IF(OR(U11="",U15=""),"",U11-U6*U15) | V13: 8790.3859 | W13: =IF(OR(W11="",W15=""),"",W11-W6*W15) | X13: =IF(OR(X11="",X15=""),"",X11-X6*X15) | Y13: =IF(OR(Y11="",Y15=""),"",Y11-Y6*Y15) | Z13: =IF(OR(Z11="",Z15=""),"",Z11-Z6*Z15) | AA13: =IF(OR(AA11="",AA15=""),"",AA11-AA6*AA15) | AB13: =IF(OR(AB11="",AB15=""),"",AB11-AB6*AB15)
A14: Net operating expense / other bridge | B14: =IF(OR(B11="",B13=""),"",B11-B13) -> 4421.8548 | C14: =IF(OR(C11="",C13=""),"",C11-C13) -> 6756.0974 | D14: =IF(OR(D11="",D13=""),"",D11-D13) -> 7842.1351 | E14: =IF(OR(E11="",E13=""),"",E11-E13) -> 8795.8291 | F14: =IF(OR(F11="",F13=""),"",F11-F13) -> 7594.6948 | G14: =IF(OR(G11="",G13=""),"",G11-G13) -> 9045.3893 | H14: =IF(OR(H11="",H13=""),"",H11-H13) -> 11460.861 | I14: =IF(OR(I11="",I13=""),"",I11-I13) -> 10998.945 | ... R14: =IF(OR(R11="",R13=""),"",R11-R13) -> 2656.0453 | V14: =IF(OR(V11="",V13=""),"",V11-V13) -> 3632.9375
A15: Net operating expense / revenue | B15: =IFERROR(IF(OR(B6="",B6=0,B14=""),"",B14/B6),"") -> 0.07294239 | C15: =IFERROR(IF(OR(C6="",C6=0,C14=""),"",C14/C6),"") -> 0.099280397 | D15: =IFERROR(IF(OR(D6="",D6=0,D14=""),"",D14/D6),"") -> 0.10679311 | E15: =IFERROR(IF(OR(E6="",E6=0,E14=""),"",E14/E6),"") -> 0.060436726 | F15: =IFERROR(IF(OR(F6="",F6=0,F14=""),"",F14/F6),"") -> 0.045871244 | G15: =IFERROR(IF(OR(G6="",G6=0,G14=""),"",G14/G6),"") -> 0.051581553 | H15: =IFERROR(IF(OR(H6="",H6=0,H14=""),"",H14/H6),"") -> 0.062947856 | I15: =IFERROR(IF(OR(I6="",I6=0,I14=""),"",I14/I6),"") -> 0.054119459 | ... R15: =IFERROR(IF(OR(R6="",R6=0,R14=""),"",R14/R6),"") -> 0.049138556 | S15: =IF(Assumptions!S29="","",Assumptions!S29) | T15: =IF(Assumptions!T29="","",Assumptions!T29) | U15: =IF(Assumptions!U29="","",Assumptions!U29) | V15: =IFERROR(IF(OR(V6="",V6=0,V14=""),"",V14/V6),"") -> 0.055665516 | W15: =IF(Assumptions!W29="","",Assumptions!W29) | X15: =IF(Assumptions!X29="","",Assumptions!X29) | Y15: =IF(Assumptions!Y29="","",Assumptions!Y29) | Z15: =IF(Assumptions!Z29="","",Assumptions!Z29) | AA15: =IF(Assumptions!AA29="","",Assumptions!AA29) | AB15: =IF(Assumptions!AB29="","",Assumptions!AB29)
A16: Attributable net income — filing actual / forecast | B16: 10610.38 | C16: 10129.985 | D16: 10041.428 | E16: 24648.748 | F16: 16233.626 | G16: 16815.756 | H16: 13033.067 | I16: 12527.201 | J16: 4157.3792 | K16: 4016.9934 | L16: 2918.9516 | M16: 1939.7425 | N16: 3082.0662 | O16: 3040.6634 | P16: 3034.5587 | Q16: 3369.9128 | R16: 3717.7079 | S16: =IF(OR(S13="",S17=""),"",S13*S17) | T16: =IF(OR(T13="",T17=""),"",T13*T17) | U16: =IF(OR(U13="",U17=""),"",U13*U17) | V16: 6345.2557 | W16: =IF(OR(W13="",W17=""),"",W13*W17) | X16: =IF(OR(X13="",X17=""),"",X13*X17) | Y16: =IF(OR(Y13="",Y17=""),"",Y13*Y17) | Z16: =IF(OR(Z13="",Z17=""),"",Z13*Z17) | AA16: =IF(OR(AA13="",AA17=""),"",AA13*AA17) | AB16: =IF(OR(AB13="",AB17=""),"",AB13*AB17)
A17: Operating profit to attributable NI conversion | B17: =IFERROR(IF(OR(B13="",B13=0,B16=""),"",B16/B13),"") -> 0.65964513 | C17: =IFERROR(IF(OR(C13="",C13=0,C16=""),"",C16/C13),"") -> 0.82377957 | D17: =IFERROR(IF(OR(D13="",D13=0,D16=""),"",D16/D13),"") -> 0.84917453 | E17: =IFERROR(IF(OR(E13="",E13=0,E16=""),"",E16/E13),"") -> 0.83766682 | F17: =IFERROR(IF(OR(F13="",F13=0,F16=""),"",F16/F13),"") -> 0.81828622 | G17: =IFERROR(IF(OR(G13="",G13=0,G16=""),"",G16/G13),"") -> 0.82473889 | H17: =IFERROR(IF(OR(H13="",H13=0,H16=""),"",H16/H13),"") -> 0.72544265 | I17: =IFERROR(IF(OR(I13="",I13=0,I16=""),"",I16/I13),"") -> 0.75166016 | ... R17: =IFERROR(IF(OR(R13="",R13=0,R16=""),"",R16/R13),"") -> 0.70082208 | S17: =IF(Assumptions!S30="","",Assumptions!S30) | T17: =IF(Assumptions!T30="","",Assumptions!T30) | U17: =IF(Assumptions!U30="","",Assumptions!U30) | V17: =IFERROR(IF(OR(V13="",V13=0,V16=""),"",V16/V13),"") -> 0.7218404 | W17: =IF(Assumptions!W30="","",Assumptions!W30) | X17: =IF(Assumptions!X30="","",Assumptions!X30) | Y17: =IF(Assumptions!Y30="","",Assumptions!Y30) | Z17: =IF(Assumptions!Z30="","",Assumptions!Z30) | AA17: =IF(Assumptions!AA30="","",Assumptions!AA30) | AB17: =IF(Assumptions!AB30="","",Assumptions!AB30)

Sheet Cash Flow
A1: Cash Flow
A2: Capex is cash paid to acquire/build fixed, intangible and other long-term assets.
A4: RMB mm unless stated | B4: 2018A | C4: 2019A | D4: 2020A | E4: 2021A | F4: 2022A | G4: 2023A | H4: 2024A | I4: 2025A | J4: 2024Q1A | K4: 2024Q2A | L4: 2024Q3A | M4: 2024Q4A | N4: 2025Q1A | O4: 2025Q2A | P4: 2025Q3A | Q4: 2025Q4A | R4: 2026Q1A | S4: 2026E | T4: 2027E | U4: 2028E | V4: 2026Q2A | W4: 2026Q3E | X4: 2026Q4E | Y4: 2027Q1E | Z4: 2027Q2E | AA4: 2027Q3E | AB4: 2027Q4E
A5: Operating cash flow (CFO) | B5: 19257.494 | C5: 25932.941 | D5: 16849.706 | E5: 27922.292 | F5: 36336.825 | G5: 26796.753 | H5: 30053.435 | I5: 33105.189 | J5: 3083.6637 | K5: 7207.6084 | L5: 9014.2075 | M5: 10747.956 | N5: 581.15851 | O5: 9946.9455 | P5: 6493.4707 | Q5: 16083.615 | R5: 6856.9172 | S5: =IF('Consol P&L'!S16="","",'Consol P&L'!S16*IFERROR(I8,1)) | T5: =IF('Consol P&L'!T16="","",'Consol P&L'!T16*IFERROR(I8,1)) | U5: =IF('Consol P&L'!U16="","",'Consol P&L'!U16*IFERROR(I8,1)) | V5: 4927.2238 | W5: =IF('Consol P&L'!W16="","",'Consol P&L'!W16*IFERROR(R8,1)) | X5: =IF('Consol P&L'!X16="","",'Consol P&L'!X16*IFERROR(R8,1)) | Y5: =IF('Consol P&L'!Y16="","",'Consol P&L'!Y16*IFERROR(R8,1)) | Z5: =IF('Consol P&L'!Z16="","",'Consol P&L'!Z16*IFERROR(R8,1)) | AA5: =IF('Consol P&L'!AA16="","",'Consol P&L'!AA16*IFERROR(R8,1)) | AB5: =IF('Consol P&L'!AB16="","",'Consol P&L'!AB16*IFERROR(R8,1))
A6: Capital expenditure — cash outflow | B6: 10279.01 | C6: 17814.815 | D6: 23235.682 | E6: 26999.583 | F6: 32656.553 | G6: 43098.415 | H6: 35830.125 | I6: 30711.201 | J6: 11092.109 | K6: 8973.3593 | L6: 9688.7514 | M6: 6075.9054 | N6: 9088.4926 | O6: 7941.419 | P6: 6722.6236 | Q6: 6958.6661 | R6: 5030.1313 | S6: =IF(OR('Consol P&L'!S6="",Assumptions!S31=""),"",'Consol P&L'!S6*Assumptions!S31) | T6: =IF(OR('Consol P&L'!T6="",Assumptions!T31=""),"",'Consol P&L'!T6*Assumptions!T31) | U6: =IF(OR('Consol P&L'!U6="",Assumptions!U31=""),"",'Consol P&L'!U6*Assumptions!U31) | V6: 5709.7598 | W6: =IF(OR('Consol P&L'!W6="",Assumptions!W31=""),"",'Consol P&L'!W6*Assumptions!W31) | X6: =IF(OR('Consol P&L'!X6="",Assumptions!X31=""),"",'Consol P&L'!X6*Assumptions!X31) | Y6: =IF(OR('Consol P&L'!Y6="",Assumptions!Y31=""),"",'Consol P&L'!Y6*Assumptions!Y31) | Z6: =IF(OR('Consol P&L'!Z6="",Assumptions!Z31=""),"",'Consol P&L'!Z6*Assumptions!Z31) | AA6: =IF(OR('Consol P&L'!AA6="",Assumptions!AA31=""),"",'Consol P&L'!AA6*Assumptions!AA31) | AB6: =IF(OR('Consol P&L'!AB6="",Assumptions!AB31=""),"",'Consol P&L'!AB6*Assumptions!AB31)
A7: Simplified free cash flow | B7: =IF(OR(B5="",B6=""),"",B5-B6) -> 8978.4844 | C7: =IF(OR(C5="",C6=""),"",C5-C6) -> 8118.1266 | D7: =IF(OR(D5="",D6=""),"",D5-D6) -> -6385.9764 | E7: =IF(OR(E5="",E6=""),"",E5-E6) -> 922.7093 | F7: =IF(OR(F5="",F6=""),"",F5-F6) -> 3680.2723 | G7: =IF(OR(G5="",G6=""),"",G5-G6) -> -16301.663 | H7: =IF(OR(H5="",H6=""),"",H5-H6) -> -5776.6896 | I7: =IF(OR(I5="",I6=""),"",I5-I6) -> 2393.9882 | ... AB7: =IF(OR(AB5="",AB6=""),"",AB5-AB6)
A8: CFO / attributable net income | B8: =IFERROR(IF(OR(B5="",'Consol P&L'!B16="",'Consol P&L'!B16=0),"",B5/'Consol P&L'!B16),"") -> 1.8149675 | C8: =IFERROR(IF(OR(C5="",'Consol P&L'!C16="",'Consol P&L'!C16=0),"",C5/'Consol P&L'!C16),"") -> 2.5600177 | D8: =IFERROR(IF(OR(D5="",'Consol P&L'!D16="",'Consol P&L'!D16=0),"",D5/'Consol P&L'!D16),"") -> 1.6780189 | E8: =IFERROR(IF(OR(E5="",'Consol P&L'!E16="",'Consol P&L'!E16=0),"",E5/'Consol P&L'!E16),"") -> 1.1328077 | F8: =IFERROR(IF(OR(F5="",'Consol P&L'!F16="",'Consol P&L'!F16=0),"",F5/'Consol P&L'!F16),"") -> 2.2383677 | G8: =IFERROR(IF(OR(G5="",'Consol P&L'!G16="",'Consol P&L'!G16=0),"",G5/'Consol P&L'!G16),"") -> 1.5935503 | H8: =IFERROR(IF(OR(H5="",'Consol P&L'!H16="",'Consol P&L'!H16=0),"",H5/'Consol P&L'!H16),"") -> 2.3059374 | I8: =IFERROR(IF(OR(I5="",'Consol P&L'!I16="",'Consol P&L'!I16=0),"",I5/'Consol P&L'!I16),"") -> 2.6426645 | ... AB8: =IFERROR(IF(OR(AB5="",'Consol P&L'!AB16="",'Consol P&L'!AB16=0),"",AB5/'Consol P&L'!AB16),"")
A9: Capex / consolidated revenue | B9: =IFERROR(IF(OR(B6="",'Consol P&L'!B6="",'Consol P&L'!B6=0),"",B6/'Consol P&L'!B6),"") -> 0.16956133 | C9: =IFERROR(IF(OR(C6="",'Consol P&L'!C6="",'Consol P&L'!C6=0),"",C6/'Consol P&L'!C6),"") -> 0.2617875 | D9: =IFERROR(IF(OR(D6="",'Consol P&L'!D6="",'Consol P&L'!D6=0),"",D6/'Consol P&L'!D6),"") -> 0.31642031 | E9: =IFERROR(IF(OR(E6="",'Consol P&L'!E6="",'Consol P&L'!E6=0),"",E6/'Consol P&L'!E6),"") -> 0.18551593 | F9: =IFERROR(IF(OR(F6="",'Consol P&L'!F6="",'Consol P&L'!F6=0),"",F6/'Consol P&L'!F6),"") -> 0.19724252 | G9: =IFERROR(IF(OR(G6="",'Consol P&L'!G6="",'Consol P&L'!G6=0),"",G6/'Consol P&L'!G6),"") -> 0.24576976 | H9: =IFERROR(IF(OR(H6="",'Consol P&L'!H6="",'Consol P&L'!H6=0),"",H6/'Consol P&L'!H6),"") -> 0.19679408 | I9: =IFERROR(IF(OR(I6="",'Consol P&L'!I6="",'Consol P&L'!I6=0),"",I6/'Consol P&L'!I6),"") -> 0.15111209 | ... AB9: =IFERROR(IF(OR(AB6="",'Consol P&L'!AB6="",'Consol P&L'!AB6=0),"",AB6/'Consol P&L'!AB6),"")

Sheet Spread Beta
A1: Spread Beta
A2: N<8 comparable quarterly observations: proportional sensitivity only; no regression beta.
A4: Field | B4: Value | C4: Unit / interpretation | D4: Low | E4: Base | F4: High | G4: Source / note | H4: Status
A5: Selected method | B5: Proportional sensitivity | C5: text | G5: N<8 quarterly observations; no regression. | H5: OK
A6: Comparable quarterly sample N | B6: 5 | C6: quarters | G6: 2024Q1/Q3, 2025Q1/Q3, 2026Q1 only. | H6: OK
A7: Regression eligibility | B7: No | C7: requires >=8 quarters | G7: Gate enforced. | H7: OK
A8: Sensitivity factor | B8: 0.77 | C8: benzene factor | G8: Model methodology assumption; not a filing fact. | H8: OK
A9: Historical data status | B9: Complete | C9: period coverage | G9: Quarterly segment costs intentionally blank. | H9: OK

Sheet Sources
A1: Sources
A2: One row per hardcoded model cell; disclosure gaps are explicit and use Cell="-".
A4: Sheet | B4: Cell | C4: Field | D4: Status type | E4: Period | F4: Source / document | G4: Document date | H4: Page / reference | I4: URL | J4: Unit | K4: Boundary / methodology note | L4: Verified?
A5: Price Inputs | B5: C6 | C5: Pure benzene market average | D5: Filing actual | E5: 2019A | F5: 2019年主要经营数据公告 | G5: 2020-03-30 | H5: Operating-data announcement | I5: https://static.cninfo.com.cn/finalpage/2020-03-31/1207432751.PDF | J5: RMB/t | K5: Company-disclosed market average; not realized price. | L5: Yes
A6: Price Inputs | B6: D6 | C6: Pure benzene market average | D6: Filing actual | E6: 2020A | F6: 万华化学2020年主要经营数据公告 | G6: 2021-03-15 | H6: Operating-data announcement | I6: https://static.cninfo.com.cn/finalpage/2021-03-16/1209385163.PDF | J6: RMB/t | K6: Company-disclosed market average; not realized price. | L6: Yes
A7: Price Inputs | B7: E6 | C7: Pure benzene market average | D7: Filing actual | E7: 2021A | F7: 万华化学2021年主要经营数据公告 | G7: 2022-03-14 | H7: Operating-data announcement | I7: https://static.cninfo.com.cn/finalpage/2022-03-15/1212567898.PDF | J7: RMB/t | K7: Company-disclosed market average; not realized price. | L7: Yes
A8: Price Inputs | B8: F6 | C8: Pure benzene market average | D8: Filing actual | E8: 2022A | F8: 万华化学2022年主要经营数据公告 | G8: 2023-03-20 | H8: Operating-data announcement | I8: https://static.cninfo.com.cn/finalpage/2023-03-21/1216168751.PDF | J8: RMB/t | K8: Company-disclosed market average; not realized price. | L8: Yes
A9: Price Inputs | B9: G5 | C9: Polymeric MDI market average | D9: Filing actual | E9: 2023A | F9: 万华化学2023年主要经营数据公告 | G9: 2024-03-18 | H9: Operating-data announcement | I9: https://static.cninfo.com.cn/finalpage/2024-03-19/1219331074.PDF | J9: RMB/t | K9: Company-disclosed market average; not realized price. | L9: Yes
A10: Price Inputs | B10: G6 | C10: Pure benzene market average | D10: Filing actual | E10: 2023A | F10: 万华化学2023年主要经营数据公告 | G10: 2024-03-18 | H10: Operating-data announcement | I10: https://static.cninfo.com.cn/finalpage/2024-03-19/1219331074.PDF | J10: RMB/t | K10: Company-disclosed market average; not realized price. | L10: Yes
A11: Price Inputs | B11: H5 | C11: Polymeric MDI market average | D11: Filing actual | E11: 2024A | F11: 万华化学2024年度主要经营数据公告 | G11: 2025-04-14 | H11: Operating-data announcement | I11: https://static.cninfo.com.cn/finalpage/2025-04-15/1223097321.PDF | J11: RMB/t | K11: Company-disclosed market average; not realized price. | L11: Yes
A12: Price Inputs | B12: H6 | C12: Pure benzene market average | D12: Filing actual | E12: 2024A | F12: 万华化学2024年度主要经营数据公告 | G12: 2025-04-14 | H12: Operating-data announcement | I12: https://static.cninfo.com.cn/finalpage/2025-04-15/1223097321.PDF | J12: RMB/t | K12: Company-disclosed market average; not realized price. | L12: Yes
A13: Price Inputs | B13: I5 | C13: Polymeric MDI market average | D13: Filing actual | E13: 2025A | F13: 万华化学2025年度主要经营数据公告 | G13: 2026-04-20 | H13: Operating-data announcement | I13: https://static.cninfo.com.cn/finalpage/2026-04-21/1225130690.PDF | J13: RMB/t | K13: Company-disclosed market average; not realized price. | L13: Yes
A14: Price Inputs | B14: I6 | C14: Pure benzene market average | D14: Filing actual | E14: 2025A | F14: 万华化学2025年度主要经营数据公告 | G14: 2026-04-20 | H14: Operating-data announcement | I14: https://static.cninfo.com.cn/finalpage/2026-04-21/1225130690.PDF | J14: RMB/t | K14: Company-disclosed market average; not realized price. | L14: Yes
A15: Price Inputs | B15: J5 | C15: Polymeric MDI market average | D15: Filing actual | E15: 2024Q1A | F15: 万华化学2024年第一季度主要经营数据公告 | G15: 2024-04-18 | H15: Operating-data announcement | I15: https://static.cninfo.com.cn/finalpage/2024-04-19/1219664107.PDF | J15: RMB/t | K15: Company-disclosed market average; not realized price. | L15: Yes
... A313: Price Inputs | B313: - | C313: Standalone quarterly PMDI / benzene market average | D313: Disclosure gap | E313: 2025Q4A | F313: 万华化学2025年度主要经营数据公告 | G313: 2026-04-20 | H313: Disclosure boundary | I313: https://static.cninfo.com.cn/finalpage/2026-04-21/1225130690.PDF | J313: N/A | K313: Standalone Q2/Q4 average is not explicitly disclosed; no inferred average is used. | L313: Yes — blank is intentional
A314: Cost Bridge | B314: - | C314: 聚氨酯系列 quarterly product-series cost / raw share | D314: Disclosure gap | E314: 2024Q1A | F314: Quarterly report / operating-data announcement | G314: See period Sources URLs | H314: Disclosure boundary | J314: N/A | K314: Quarterly segment cost and cost composition are not disclosed; left blank and no allocation is forced. | L314: Yes — blank is intentional
A315: Cost Bridge | B315: - | C315: 聚氨酯系列 quarterly product-series cost / raw share | D315: Disclosure gap | E315: 2024Q2A | F315: Quarterly report / operating-data announcement | G315: See period Sources URLs | H315: Disclosure boundary | J315: N/A | K315: Quarterly segment cost and cost composition are not disclosed; left blank and no allocation is forced. | L315: Yes — blank is intentional
A316: Cost Bridge | B316: - | C316: 聚氨酯系列 quarterly product-series cost / raw share | D316: Disclosure gap | E316: 2024Q3A | F316: Quarterly report / operating-data announcement | G316: See period Sources URLs | H316: Disclosure boundary | J316: N/A | K316: Quarterly segment cost and cost composition are not disclosed; left blank and no allocation is forced. | L316: Yes — blank is intentional
A317: Cost Bridge | B317: - | C317: 聚氨酯系列 quarterly product-series cost / raw share | D317: Disclosure gap | E317: 2024Q4A | F317: Quarterly report / operating-data announcement | G317: See period Sources URLs | H317: Disclosure boundary | J317: N/A | K317: Quarterly segment cost and cost composition are not disclosed; left blank and no allocation is forced. | L317: Yes — blank is intentional
A318: Cost Bridge | B318: - | C318: 聚氨酯系列 quarterly product-series cost / raw share | D318: Disclosure gap | E318: 2025Q1A | F318: Quarterly report / operating-data announcement | G318: See period Sources URLs | H318: Disclosure boundary | J318: N/A | K318: Quarterly segment cost and cost composition are not disclosed; left blank and no allocation is forced. | L318: Yes — blank is intentional
A319: Cost Bridge | B319: - | C319: 聚氨酯系列 quarterly product-series cost / raw share | D319: Disclosure gap | E319: 2025Q2A | F319: Quarterly report / operating-data announcement | G319: See period Sources URLs | H319: Disclosure boundary | J319: N/A | K319: Quarterly segment cost and cost composition are not disclosed; left blank and no allocation is forced. | L319: Yes — blank is intentional
A320: Cost Bridge | B320: - | C320: 聚氨酯系列 quarterly product-series cost / raw share | D320: Disclosure gap | E320: 2025Q3A | F320: Quarterly report / operating-data announcement | G320: See period Sources URLs | H320: Disclosure boundary | J320: N/A | K320: Quarterly segment cost and cost composition are not disclosed; left blank and no allocation is forced. | L320: Yes — blank is intentional
A321: Cost Bridge | B321: - | C321: 聚氨酯系列 quarterly product-series cost / raw share | D321: Disclosure gap | E321: 2025Q4A | F321: Quarterly report / operating-data announcement | G321: See period Sources URLs | H321: Disclosure boundary | J321: N/A | K321: Quarterly segment cost and cost composition are not disclosed; left blank and no allocation is forced. | L321: Yes — blank is intentional
A322: Cost Bridge | B322: - | C322: 聚氨酯系列 quarterly product-series cost / raw share | D322: Disclosure gap | E322: 2026Q1A | F322: Quarterly report / operating-data announcement | G322: See period Sources URLs | H322: Disclosure boundary | J322: N/A | K322: Quarterly segment cost and cost composition are not disclosed; left blank and no allocation is forced. | L322: Yes — blank is intentional
A323: Cost Bridge | B323: - | C323: 石化系列 quarterly product-series cost / raw share | D323: Disclosure gap | E323: 2024Q1A | F323: Quarterly report / operating-data announcement | G323: See period Sources URLs | H323: Disclosure boundary | J323: N/A | K323: Quarterly segment cost and cost composition are not disclosed; left blank and no allocation is forced. | L323: Yes — blank is intentional
A324: Cost Bridge | B324: - | C324: 石化系列 quarterly product-series cost / raw share | D324: Disclosure gap | E324: 2024Q2A | F324: Quarterly report / operating-data announcement | G324: See period Sources URLs | H324: Disclosure boundary | J324: N/A | K324: Quarterly segment cost and cost composition are not disclosed; left blank and no allocation is forced. | L324: Yes — blank is intentional
A325: Cost Bridge | B325: - | C325: 石化系列 quarterly product-series cost / raw share | D325: Disclosure gap | E325: 2024Q3A | F325: Quarterly report / operating-data announcement | G325: See period Sources URLs | H325: Disclosure boundary | J325: N/A | K325: Quarterly segment cost and cost composition are not disclosed; left blank and no allocation is forced. | L325: Yes — blank is intentional
... A340: Cost Bridge | B340: - | C340: 精细化学品及新材料系列 quarterly product-series cost / raw share | D340: Disclosure gap | E340: 2026Q1A | F340: Quarterly report / operating-data announcement | G340: See period Sources URLs | H340: Disclosure boundary | J340: N/A | K340: Quarterly segment cost and cost composition are not disclosed; left blank and no allocation is forced. | L340: Yes — blank is intentional
A341: Segment P&L | B341: - | C341: Eliminations revenue | D341: Disclosure gap | E341: 2018A | F341: 2018年年度报告 | G341: 2019-04-22 | H341: Disclosure boundary | I341: https://static.cninfo.com.cn/finalpage/2019-04-23/1206073832.PDF | J341: N/A | K341: No separate eliminations line disclosed in the annual product table; boundary residual formula preserves reconciliation. | L341: Yes — blank is intentional
A342: Segment P&L | B342: - | C342: Eliminations cost | D342: Disclosure gap | E342: 2018A | F342: 2018年年度报告 | G342: 2019-04-22 | H342: Disclosure boundary | I342: https://static.cninfo.com.cn/finalpage/2019-04-23/1206073832.PDF | J342: N/A | K342: No separate eliminations line disclosed in the annual product table; boundary residual formula preserves reconciliation. | L342: Yes — blank is intentional
A343: Segment P&L | B343: - | C343: Eliminations revenue | D343: Disclosure gap | E343: 2019A | F343: 2019年年度报告 | G343: 2020-03-30 | H343: Disclosure boundary | I343: https://static.cninfo.com.cn/finalpage/2020-03-31/1207432775.PDF | J343: N/A | K343: No separate eliminations line disclosed in the annual product table; boundary residual formula preserves reconciliation. | L343: Yes — blank is intentional
A344: Segment P&L | B344: - | C344: Eliminations cost | D344: Disclosure gap | E344: 2019A | F344: 2019年年度报告 | G344: 2020-03-30 | H344: Disclosure boundary | I344: https://static.cninfo.com.cn/finalpage/2020-03-31/1207432775.PDF | J344: N/A | K344: No separate eliminations line disclosed in the annual product table; boundary residual formula preserves reconciliation. | L344: Yes — blank is intentional
A345: Segment P&L | B345: - | C345: Eliminations revenue | D345: Disclosure gap | E345: 2020A | F345: 万华化学2020年度报告 | G345: 2021-03-15 | H345: Disclosure boundary | I345: https://static.cninfo.com.cn/finalpage/2021-03-16/1209385146.PDF | J345: N/A | K345: No separate eliminations line disclosed in the annual product table; boundary residual formula preserves reconciliation. | L345: Yes — blank is intentional
A346: Segment P&L | B346: - | C346: Eliminations cost | D346: Disclosure gap | E346: 2020A | F346: 万华化学2020年度报告 | G346: 2021-03-15 | H346: Disclosure boundary | I346: https://static.cninfo.com.cn/finalpage/2021-03-16/1209385146.PDF | J346: N/A | K346: No separate eliminations line disclosed in the annual product table; boundary residual formula preserves reconciliation. | L346: Yes — blank is intentional
A347: Volume-Price | B347: V6 | C347: 聚氨酯系列 disclosed sales volume | D347: Formula / derived | E347: 2026Q2A | F347: 2026H1与2026Q1主要经营数据公告 | G347: 2026-08-24 | H347: H1 report less Q1 report | I347: https://static.cninfo.com.cn/finalpage/2026-08-25/1225497206.PDF ; https://static.cninfo.com.cn/finalpage/2026-04-21/1225130804.PDF | J347: 10kt | K347: H1 cumulative minus Q1; volume includes internal use; revenue includes trade/internal-use where disclosed. | L347: Yes
A348: Volume-Price | B348: V8 | C348: 聚氨酯系列 product-series revenue | D348: Formula / derived | E348: 2026Q2A | F348: 2026H1与2026Q1主要经营数据公告 | G348: 2026-08-24 | H348: H1 report less Q1 report | I348: https://static.cninfo.com.cn/finalpage/2026-08-25/1225497206.PDF ; https://static.cninfo.com.cn/finalpage/2026-04-21/1225130804.PDF | J348: RMB mm | K348: H1 cumulative minus Q1; volume includes internal use; revenue includes trade/internal-use where disclosed. | L348: Yes
A349: Volume-Price | B349: V16 | C349: 石化系列 disclosed sales volume | D349: Formula / derived | E349: 2026Q2A | F349: 2026H1与2026Q1主要经营数据公告 | G349: 2026-08-24 | H349: H1 report less Q1 report | I349: https://static.cninfo.com.cn/finalpage/2026-08-25/1225497206.PDF ; https://static.cninfo.com.cn/finalpage/2026-04-21/1225130804.PDF | J349: 10kt | K349: H1 cumulative minus Q1; volume includes internal use; revenue includes trade/internal-use where disclosed. | L349: Yes
A350: Volume-Price | B350: V18 | C350: 石化系列 product-series revenue | D350: Formula / derived | E350: 2026Q2A | F350: 2026H1与2026Q1主要经营数据公告 | G350: 2026-08-24 | H350: H1 report less Q1 report | I350: https://static.cninfo.com.cn/finalpage/2026-08-25/1225497206.PDF ; https://static.cninfo.com.cn/finalpage/2026-04-21/1225130804.PDF | J350: RMB mm | K350: H1 cumulative minus Q1; volume includes internal use; revenue includes trade/internal-use where disclosed. | L350: Yes
A351: Volume-Price | B351: V26 | C351: 精细化学品及新材料系列 disclosed sales volume | D351: Formula / derived | E351: 2026Q2A | F351: 2026H1与2026Q1主要经营数据公告 | G351: 2026-08-24 | H351: H1 report less Q1 report | I351: https://static.cninfo.com.cn/finalpage/2026-08-25/1225497206.PDF ; https://static.cninfo.com.cn/finalpage/2026-04-21/1225130804.PDF | J351: 10kt | K351: H1 cumulative minus Q1; volume includes internal use; revenue includes trade/internal-use where disclosed. | L351: Yes
A352: Volume-Price | B352: V28 | C352: 精细化学品及新材料系列 product-series revenue | D352: Formula / derived | E352: 2026Q2A | F352: 2026H1与2026Q1主要经营数据公告 | G352: 2026-08-24 | H352: H1 report less Q1 report | I352: https://static.cninfo.com.cn/finalpage/2026-08-25/1225497206.PDF ; https://static.cninfo.com.cn/finalpage/2026-04-21/1225130804.PDF | J352: RMB mm | K352: H1 cumulative minus Q1; volume includes internal use; revenue includes trade/internal-use where disclosed. | L352: Yes
... A358: Cash Flow | B358: V6 | C358: Capital expenditure — cash outflow | D358: Formula / derived | E358: 2026Q2A | F358: 2026H1报告与2026Q1报告 | G358: 2026-08-24 | H358: H1 report less Q1 report | I358: https://static.cninfo.com.cn/finalpage/2026-08-25/1225497561.PDF ; https://static.cninfo.com.cn/finalpage/2026-04-21/1225130687.PDF | J358: RMB mm | K358: H1 cumulative filing actual less Q1 filing actual; arithmetic difference, not an estimate. | L358: Yes

Sheet Checks
A1: Checks
A2: All checks must be OK after LibreOffice recalculation.
A4: Check | B4: Value / difference | C4: Tolerance | D4: Status | E4: Notes | F4: Last run
A5: Exact period header standard | B5: =IF(AND(Assumptions!B4="2018A",Assumptions!I4="2025A",Assumptions!J4="2024Q1A",Assumptions!R4="2026Q1A",Assumptions!S4="2026E",Assumptions!U4="2028E",Assumptions!V4="2026Q2A",Assumptions!W4="2026Q3E",Assumptions!AB4="2027Q4E"),0,1) -> 0 | C5: 0 | D5: =IF(B5=C5,"OK","ERROR") -> OK | E5: 27 period columns; 2026Q2 actual inserted, quarterly forecasts now 2026Q3E–2027Q4E.
A6: 2018A Revenue bridge | B6: ='Consol P&L'!B7 -> 0 | C6: 0.01 | D6: =IF(ABS(B6)<=C6,"OK","ERROR") -> OK | E6: RMB mm; product schedule plus boundary residual must reconcile.
A7: 2018A Cost bridge | B7: ='Consol P&L'!B10 -> 0 | C7: 0.01 | D7: =IF(ABS(B7)<=C7,"OK","ERROR") -> OK | E7: RMB mm; product schedule plus boundary residual must reconcile.
A8: 2019A Revenue bridge | B8: ='Consol P&L'!C7 -> 0 | C8: 0.01 | D8: =IF(ABS(B8)<=C8,"OK","ERROR") -> OK | E8: RMB mm; product schedule plus boundary residual must reconcile.
A9: 2019A Cost bridge | B9: ='Consol P&L'!C10 -> 0 | C9: 0.01 | D9: =IF(ABS(B9)<=C9,"OK","ERROR") -> OK | E9: RMB mm; product schedule plus boundary residual must reconcile.
A10: 2020A Revenue bridge | B10: ='Consol P&L'!D7 -> 0 | C10: 0.01 | D10: =IF(ABS(B10)<=C10,"OK","ERROR") -> OK | E10: RMB mm; product schedule plus boundary residual must reconcile.
A11: 2020A Cost bridge | B11: ='Consol P&L'!D10 -> 0 | C11: 0.01 | D11: =IF(ABS(B11)<=C11,"OK","ERROR") -> OK | E11: RMB mm; product schedule plus boundary residual must reconcile.
A12: 2021A Revenue bridge | B12: ='Consol P&L'!E7 -> 0 | C12: 0.01 | D12: =IF(ABS(B12)<=C12,"OK","ERROR") -> OK | E12: RMB mm; product schedule plus boundary residual must reconcile.
A13: 2021A Cost bridge | B13: ='Consol P&L'!E10 -> 0 | C13: 0.01 | D13: =IF(ABS(B13)<=C13,"OK","ERROR") -> OK | E13: RMB mm; product schedule plus boundary residual must reconcile.
A14: 2022A Revenue bridge | B14: ='Consol P&L'!F7 -> 0 | C14: 0.01 | D14: =IF(ABS(B14)<=C14,"OK","ERROR") -> OK | E14: RMB mm; product schedule plus boundary residual must reconcile.
A15: 2022A Cost bridge | B15: ='Consol P&L'!F10 -> 0 | C15: 0.01 | D15: =IF(ABS(B15)<=C15,"OK","ERROR") -> OK | E15: RMB mm; product schedule plus boundary residual must reconcile.
A16: 2023A Revenue bridge | B16: ='Consol P&L'!G7 -> 0 | C16: 0.01 | D16: =IF(ABS(B16)<=C16,"OK","ERROR") -> OK | E16: RMB mm; product schedule plus boundary residual must reconcile.
A17: 2023A Cost bridge | B17: ='Consol P&L'!G10 -> 0 | C17: 0.01 | D17: =IF(ABS(B17)<=C17,"OK","ERROR") -> OK | E17: RMB mm; product schedule plus boundary residual must reconcile.
A18: 2024A Revenue bridge | B18: ='Consol P&L'!H7 -> 0 | C18: 0.01 | D18: =IF(ABS(B18)<=C18,"OK","ERROR") -> OK | E18: RMB mm; product schedule plus boundary residual must reconcile.
A19: 2024A Cost bridge | B19: ='Consol P&L'!H10 -> 0 | C19: 0.01 | D19: =IF(ABS(B19)<=C19,"OK","ERROR") -> OK | E19: RMB mm; product schedule plus boundary residual must reconcile.
A20: 2025A Revenue bridge | B20: ='Consol P&L'!I7 -> 0 | C20: 0.01 | D20: =IF(ABS(B20)<=C20,"OK","ERROR") -> OK | E20: RMB mm; product schedule plus boundary residual must reconcile.
A21: 2025A Cost bridge | B21: ='Consol P&L'!I10 -> 0 | C21: 0.01 | D21: =IF(ABS(B21)<=C21,"OK","ERROR") -> OK | E21: RMB mm; product schedule plus boundary residual must reconcile.
A22: 2024Q1A Revenue bridge | B22: ='Consol P&L'!J7 -> 0 | C22: 0.01 | D22: =IF(ABS(B22)<=C22,"OK","ERROR") -> OK | E22: RMB mm; product schedule plus boundary residual must reconcile.
A23: 2024Q1A Cost bridge | B23: ='Consol P&L'!J10 -> 0 | C23: 0.01 | D23: =IF(ABS(B23)<=C23,"OK","ERROR") -> OK | E23: RMB mm; product schedule plus boundary residual must reconcile.
A24: 2024Q2A Revenue bridge | B24: ='Consol P&L'!K7 -> 0 | C24: 0.01 | D24: =IF(ABS(B24)<=C24,"OK","ERROR") -> OK | E24: RMB mm; product schedule plus boundary residual must reconcile.
A25: 2024Q2A Cost bridge | B25: ='Consol P&L'!K10 -> 0 | C25: 0.01 | D25: =IF(ABS(B25)<=C25,"OK","ERROR") -> OK | E25: RMB mm; product schedule plus boundary residual must reconcile.
A26: 2024Q3A Revenue bridge | B26: ='Consol P&L'!L7 -> 0 | C26: 0.01 | D26: =IF(ABS(B26)<=C26,"OK","ERROR") -> OK | E26: RMB mm; product schedule plus boundary residual must reconcile.
A27: 2024Q3A Cost bridge | B27: ='Consol P&L'!L10 -> 0 | C27: 0.01 | D27: =IF(ABS(B27)<=C27,"OK","ERROR") -> OK | E27: RMB mm; product schedule plus boundary residual must reconcile.
A28: 2024Q4A Revenue bridge | B28: ='Consol P&L'!M7 -> 0 | C28: 0.01 | D28: =IF(ABS(B28)<=C28,"OK","ERROR") -> OK | E28: RMB mm; product schedule plus boundary residual must reconcile.
A29: 2024Q4A Cost bridge | B29: ='Consol P&L'!M10 -> 0 | C29: 0.01 | D29: =IF(ABS(B29)<=C29,"OK","ERROR") -> OK | E29: RMB mm; product schedule plus boundary residual must reconcile.
A30: 2025Q1A Revenue bridge | B30: ='Consol P&L'!N7 -> 0 | C30: 0.01 | D30: =IF(ABS(B30)<=C30,"OK","ERROR") -> OK | E30: RMB mm; product schedule plus boundary residual must reconcile.
A31: 2025Q1A Cost bridge | B31: ='Consol P&L'!N10 -> 0 | C31: 0.01 | D31: =IF(ABS(B31)<=C31,"OK","ERROR") -> OK | E31: RMB mm; product schedule plus boundary residual must reconcile.
A32: 2025Q2A Revenue bridge | B32: ='Consol P&L'!O7 -> 0 | C32: 0.01 | D32: =IF(ABS(B32)<=C32,"OK","ERROR") -> OK | E32: RMB mm; product schedule plus boundary residual must reconcile.
A33: 2025Q2A Cost bridge | B33: ='Consol P&L'!O10 -> 0 | C33: 0.01 | D33: =IF(ABS(B33)<=C33,"OK","ERROR") -> OK | E33: RMB mm; product schedule plus boundary residual must reconcile.
A34: 2025Q3A Revenue bridge | B34: ='Consol P&L'!P7 -> 0 | C34: 0.01 | D34: =IF(ABS(B34)<=C34,"OK","ERROR") -> OK | E34: RMB mm; product schedule plus boundary residual must reconcile.
A35: 2025Q3A Cost bridge | B35: ='Consol P&L'!P10 -> 0 | C35: 0.01 | D35: =IF(ABS(B35)<=C35,"OK","ERROR") -> OK | E35: RMB mm; product schedule plus boundary residual must reconcile.
A36: 2025Q4A Revenue bridge | B36: ='Consol P&L'!Q7 -> 0 | C36: 0.01 | D36: =IF(ABS(B36)<=C36,"OK","ERROR") -> OK | E36: RMB mm; product schedule plus boundary residual must reconcile.
A37: 2025Q4A Cost bridge | B37: ='Consol P&L'!Q10 -> 0 | C37: 0.01 | D37: =IF(ABS(B37)<=C37,"OK","ERROR") -> OK | E37: RMB mm; product schedule plus boundary residual must reconcile.
A38: 2026Q1A Revenue bridge | B38: ='Consol P&L'!R7 -> 0 | C38: 0.01 | D38: =IF(ABS(B38)<=C38,"OK","ERROR") -> OK | E38: RMB mm; product schedule plus boundary residual must reconcile.
A39: 2026Q1A Cost bridge | B39: ='Consol P&L'!R10 -> 0 | C39: 0.01 | D39: =IF(ABS(B39)<=C39,"OK","ERROR") -> OK | E39: RMB mm; product schedule plus boundary residual must reconcile.
A40: Hardcoded-cell source coverage | B40: =COUNTIFS(Sources!B5:B1000,"<>",Sources!B5:B1000,"<>-") -> 311 | C40: 311 | D40: =IF(B40=C40,"OK","ERROR") -> OK | E40: Exactly one Sources row and one cell comment per hardcoded model cell.
A41: Quarterly segment cost disclosure | B41: Not disclosed | D41: OK | E41: Quarterly product-series cost and raw-material shares are blank by design; no allocation is forced.
A42: Spread method gate | B42: ='Spread Beta'!B5 -> Proportional sensitivity | D42: =IF(B42="Proportional sensitivity","OK","ERROR") -> OK | E42: N<8 comparable quarterly observations.
A43: Blank forecast assumptions gate — consolidated revenue | B43: =IF(COUNT(Assumptions!S6:S31,Assumptions!T6:T31,Assumptions!U6:U31,Assumptions!W6:W31,Assumptions!X6:X31,Assumptions!Y6:Y31,Assumptions!Z6:Z31,Assumptions!AA6:AA31,Assumptions!AB6:AB31)=0,IF(AND('Consol P&L'!S6="",'Consol P&L'!T6="",'Consol P&L'!U6="",'Consol P&L'!W6="",'Consol P&L'!X6="",'Consol P&L'!Y6="",'Consol P&L'!Z6="",'Consol P&L'!AA6="",'Consol P&L'!AB6=""),0,1),0) -> 0 | C43: 0 | D43: =IF(B43=0,"OK","ERROR") -> OK | E43: When all forecast assumptions are blank, annual forecasts and 2026Q3E–2027Q4E revenue cells remain blank; 2026Q2A is excluded.
A44: LibreOffice formula scan | B44: 0 | C44: 0 | D44: =IF(B44=0,"OK","ERROR") -> OK | E44: Headless recalculation and full-workbook scan: 0 formula errors across 1,908 formulas. | F44: 2026-08-24 20:33 EDT | LibreOffice headless
A45: 2026Q2A Revenue bridge | B45: ='Consol P&L'!V7 -> 0 | C45: 0.01 | D45: =IF(ABS(B45)<=C45,"OK","ERROR") -> OK | E45: RMB mm; product schedule plus boundary residual must reconcile.
A46: 2026Q2A Cost bridge | B46: ='Consol P&L'!V10 -> 0 | C46: 0.01 | D46: =IF(ABS(B46)<=C46,"OK","ERROR") -> OK | E46: RMB mm; quarterly segment costs undisclosed; boundary residual reconciles to consolidated actual.
